Workbook

Sheet Cover page
D4: Ugar Sugar Works Ltd.
E7: Financial Modelling and Valuation Analysis
C10: Company : Ugar Sugar Works Ltd. | I10: xxxx | J10: Inputs / Assumptions
C11: Ticker : NSE: UGARSUGAR, BSE: 530363 | I11: xxxx | J11: Formulae
C12: Sector : FMCG | I12: xxxx | J12: Linking/ Reference cell
C13: Industry : Agricultural Food & other Products
C14: Sub-Industry: Sugar
C15: Analyst : Manish Rathour
F17: INDEX
D19: Assumptions
D20: Revenue Growth Scenarios
D21: Historical Information
D22: Comps Data
D23: Assumptions Data
D24: Working Schedules
D25: Financial Statements
D26: DCF Valuation
D27: Sensitivity Analysis
D28: Comps Valuation
D29: Ratio Analysis & Interpretation
D30: Market Returns
... D33: Valuation Summary- Football Analysis

Sheet Assumptions->

Sheet Assumptions
A1: ='Historical Info'!A1 -> Ugar Sugar Works Ltd.
A2: Assumptions
D4: Company Description | E4: Ugar Sugar Works Ltd.
D5: ISIN Code | E5: INE071E01023
D6: Sector Name | E6: FMCG
D7: Industry | E7: Agricultural Food & other Products
D8: Exchange Name | E8: NSE: UGARSUGAR, BSE: 530363
D9: Website | E9: https://www.ugarsugar.com/
D10: Company Description | E10: The Ugar Sugar Works Ltd, established in 1939 as the flagship of the Shirgaokar Group, is the largest single-location sugar producer in Southern India with a combined crushing capacity of 18,000 TCD across its Ugar Khurd and Jewargi plants. The company operates a highly integrated model, manufacturing various grades of white crystal sugar and unique export-oriented sugar cubes while leveraging byproducts for a 44 MW co-generation power plant and a 75,000-litre daily capacity distillery producing ethanol and IML brands like Old Castle and Ugar XXX Rum. Publicly traded on the NSE and BSE, the firm reported revenues of ₹1,420 Cr for FY2025 and remains a key player in India's ethanol blending initiatives under the leadership of the Shirgaokar family.
D11: Current Market Price | E11: 39.33
D50: Scenario
D51: Base Case | F51: 1
D54: Company Data
D55: Particulars | G55: Amount
D56: No of Outstanding shares | E56: Unit | G56: ='Comps (Data)'!D11*10^5 -> 1.1253063e+08
D57: Face Value per share | E57: Rs. | G57: 1
D58: Current Market Price | E58: Rs. | G58: =E11 -> 39.33
D59: Market Capitalisation | E59: INR in Lakh | G59: ='Comps (Data)'!E11 -> 44258.298
D62: Assumptions
D63: Perpetual Growth rate | E63: % | G63: =DCF!E11 -> 0.04
D64: 10 year Bond yield rate | E64: % | G64: =Market_Returns!F7 -> 0.06961
D65: Interest rate | E65: % | G65: ='Comps (Data)'!K11 -> 0.27409762
D68: Particular | E68: Assumptions
D69: Revenue Buildup | E69: Using bottom-up, segment-wise method, I computed the weighted average revenue growth rate for the company. Based on historical data, I derived Base Case revenue growth rate of 9.86% (Calculations given in Worksheet 'Assumptions (Data)'. I then forecasted revenue using this base case as the anchor, applying a +5% Premium for the Bull Case (14.86%) supported by stronger Sugar and Distellary growth projections by CRISIL, and a -5% haircut for the Bear Case to adjust for downside risks such as a correction in sugar prices and a softening of distillery demand, Climate risk etc. Since historical peer revenue CAGRs for listed Indian sugar businesses range from -2.8% to +14.8%, I selected ±5% as my sensitivity band since it is a realistic and statistically sound swing around my base estimate.
D70: Cost Buildup | E70: I have assumed COGS, Salaries & Benefits, and Other SG&A Expenses to grow at the historical average growth rate, derived from FY2021–FY2025 data, and kept constant throughout the forecast period. These cost heads are operationally linked to revenue volume and have exhibited stable historical trends, making the average growth rate the most reliable anchor for projection.
E71: D&A as a % of PP&E has ranged from 7.8% to 11.1% historically. In the forecast period, I have assumed it to gradually increase by 2% in every 3 years, starting at 8.3% in FY2026F, stepping up to 14.3% by FY2035F. Assuming that the company continues to invest in capacity expansion- particularly in the distillery and ethanol segment- the asset base deepens, leading to progressively higher depreciation charges as a proportion of PP&E over time.
E72: I have normalized the interest rate to 9.4%, representing the most recently observed stable rate in FY2025, and held it constant throughout the forecast period. Interest expense in each forecast year is calculated as 9.4% applied to the opening debt balance from the Debt & Interest Schedule. This approach reflects a stable borrowing cost assumption absent any guidance on refinancing or new debt issuances.
E73: Other Income (Expense) is assumed to grow at the average growth rate of Historical years, Keeping them constant going forward.
E74: Historically the effective tax rate has been erratic- ranging from 6.6% to 30.6%, largely due to deferred tax adjustments and prior year losses. As the company stabilizes its profitability, I have assumed a gradual convergence (by 0.5% increase in every 2 years) towards the statutory corporate tax rate of 30%, stepping up from 27% in FY2026F to 29% by FY2035F, reflecting the normalization of tax provisions over time.
D75: Balance Sheet Items | E75: I have averaged historical Capex over FY2021–FY2025 and assumed it grows at 0.5% per year through the forecast period. The adjusted Capex is allocated to PP&E in proportion to the asset composition observed in FY2025 (the latest audited year). This reflects continued but measured capital investment in Ugar's distillery and ethanol expansion without assuming step-change capacity additions.
E76: PP&E is forecasted using PP&E Schedule, Opening PP&E for each year is sourced from the closing balance of the prior year. Capex additions and depreciation charges are computed from the Depreciation Schedule in the Working Schedules tab.
E77: Bank Deposits, Other Current Assets, Goodwill, Financial Assets, Other Non-Current Assets, Other Current & Non-Current Liabilities are held constant at their FY2025 audited levels throughout the forecast period As no company disclosures, management guidance, or industry data were available to support a directional assumption.
E78: Non-Controlling Interest is assumed to be zero throughout the forecast period. Ugar Sugar Works does not have a material NCI position based on the latest audited financial statements, and no disclosures indicate any anticipated change in ownership structure.
E79: The dividend payout ratio is assumed to grow at the historical average growth rate of 10.3% per year, consistent with the company's observed payout trajectory over FY2021–FY2025. Keeping it constant throughout the forecast period. Absolute dividend outflow is derived from PAT multiplied by the forecasted payout ratio in each year.
E80: Equity Share Capital is held constant at the FY2025 level of ₹1125 Lakhs throughout the forecast period. The company has not announced any plans for a rights issue, ESOP dilution, or buyback, and the face value remains unchanged.
E81: Cash and Cash Equivalents serve as the balancing figure in the Balance Sheet for each forecast year. The closing cash balance is derived from the Cash Flow Statement (Operating + Investing + Financing cash flows), ensuring internal consistency across all three financial statements.
E82: DSO, DIO, and DPO are computed using a 365-day convention and assumed to grow at their respective historical average growth rates derived from FY2021–FY2025 data. These ratios are then used to back-calculate Trade Receivables, Inventory, and Trade Payables as a function of Revenue and COGS respectively in each forecast year.
D83: Working Capital | E83: Trade Receivables, Inventory, and Trade Payables are forecasted using the working capital turnover ratios (DSO, DIO, DPO) derived from historical averages. All three are grown at their historical average rates and are directly linked to the Revenue and COGS drivers in the Income Statement, maintaining operational consistency in working capital modeling.
D84: Cash Flow Statement | E84: Sale of PP&E: Set to zero throughout the forecast period. Ugar Sugar Works is in an active capex and capacity expansion phase. No asset disposals have been disclosed or are expected based on available information.
E85: Advance Given for Investment: Set it to zero throughout the forecast period. No guidance or disclosure supports forecasting any new investment advances; held flat to avoid speculative assumptions.
E86: Issuance/Redemption of Preference Shares (NCI): Has set it to zero throughout the forecast period. The company has no Non-Controlling Interest on its balance sheet, and no preference share activity has been disclosed.
E87: Net Proceeds from Sale of Investments: Assumed to be zero throughout the forecast period. No investment disposal activity has been disclosed by the company or is expected based on available information.
E88: Interest & Dividend Received: I have assumed it to grow at the historical average growth rate of prior years, consistent with the treatment applied to Other Income line items.
D89: DCF Assumptions | E89: Risk free rate: Set to 6.96%, derived from long-run nominal GDP growth expectations for India. This is consistent with India's historical real GDP trajectory of ~6–7% adjusted for long-term inflation normalization. Perpetual Growth Rate: Set at 4.0% to calculate Terminal value.
E90: WACC: Derived it using CAPM method.
E91: EV/EBITDA Exit Multiple: Sourced from the median peer comparable EV/EBITDA multiple derived from the Comps Valuation sheet, representing the most market-consistent terminal value anchor.

Sheet Rev Growth Scenarios
A1: ='Historical Info'!A1 -> Ugar Sugar Works Ltd.
A2: Revenue Growth Scenarios
D4: Scenarios | E4: Growth (%) | H4: ='Financial Statements'!M2 -> 2026 | I4: ='Financial Statements'!N2 -> 2027 | J4: ='Financial Statements'!O2 -> 2028 | K4: ='Financial Statements'!P2 -> 2029 | L4: ='Financial Statements'!Q2 -> 2030 | M4: ='Financial Statements'!R2 -> 2031 | N4: ='Financial Statements'!S2 -> 2032 | O4: ='Financial Statements'!T2 -> 2033 | ... Q4: ='Financial Statements'!V2 -> 2035
D5: Base Case | E5: 0.098639712 | H5: =E5 -> 0.098639712 | I5: =H5*(1-$E$8) -> 0.089268939 | J5: =I5*(1-$E$8) -> 0.08078839 | K5: =J5*(1-$E$8) -> 0.073113493 | L5: =K5*(1-$E$8) -> 0.066167711 | M5: =L5*(1-$E$8) -> 0.059881778 | N5: =M5*(1-$E$8) -> 0.054193009 | O5: =N5*(1-$E$8) -> 0.049044674 | P5: =O5*(1-$E$8) -> 0.04438543 | Q5: =P5*(1-$E$8) -> 0.040168814
D6: Bull Case | E6: =E5+0.05 -> 0.14863971 | H6: =E6 -> 0.14863971 | I6: =H6*(1-$E$8) -> 0.13451894 | J6: =I6*(1-$E$8) -> 0.12173964 | K6: =J6*(1-$E$8) -> 0.11017437 | L6: =K6*(1-$E$8) -> 0.099707809 | M6: =L6*(1-$E$8) -> 0.090235567 | N6: =M6*(1-$E$8) -> 0.081663188 | O6: =N6*(1-$E$8) -> 0.073905185 | P6: =O6*(1-$E$8) -> 0.066884192 | Q6: =P6*(1-$E$8) -> 0.060530194
D7: Bear Case | E7: =E5-0.05 -> 0.048639712 | H7: =E7 -> 0.048639712 | I7: =H7*(1-$E$8) -> 0.044018939 | J7: =I7*(1-$E$8) -> 0.03983714 | K7: =J7*(1-$E$8) -> 0.036052612 | L7: =K7*(1-$E$8) -> 0.032627613 | M7: =L7*(1-$E$8) -> 0.02952799 | N7: =M7*(1-$E$8) -> 0.026722831 | O7: =N7*(1-$E$8) -> 0.024184162 | P7: =O7*(1-$E$8) -> 0.021886667 | Q7: =P7*(1-$E$8) -> 0.019807433
D8: Annual Growth Tempering | E8: 0.095
D11: Back to Cover

Sheet Inputs->

Sheet Historical Info
A1: Ugar Sugar Works Ltd.
A2: Historical Information
A4: INCOME STATEMENT | H4: 2021 | I4: =H4+1 -> 2022 | J4: =I4+1 -> 2023 | K4: =J4+1 -> 2024 | L4: =K4+1 -> 2025
C5: Revenues
D6: Revenue From Operations | H6: 111796.48 | I6: 130158.9 | J6: 194014.95 | K6: 127723.66 | L6: 140741.27
D7: Other Income | H7: 586.52 | I7: 224.47 | J7: 642.31 | K7: 3307.94 | L7: 1339.29
D8: Total Income (I+II) | H8: =SUM(H6:H7) -> 112383 | I8: =SUM(I6:I7) -> 130383.37 | J8: =SUM(J6:J7) -> 194657.26 | K8: =SUM(K6:K7) -> 131031.6 | L8: =SUM(L6:L7) -> 142080.56
C9: Expenses
D10: (a) Cost of materials consumed | H10: 77572.52 | I10: 98413.84 | J10: 92449.88 | K10: 94241.6 | L10: 105950.84
D11: (b) Other Manufacturing Expenses | H11: 2219.92 | I11: 3195.97 | J11: 3512.82 | K11: 4432.82 | L11: 5352.22
D12: (c) Purchases of Stock-in-Trade | H12: 3930.52 | I12: 4670.84 | J12: 7352.83 | K12: 6422.66 | L12: 4021.48
D13: (d) Changes in inventories of finished goods, Stock-in-Trade and work-in-progress | H13: -4320.56 | I13: -13653.24 | J13: 40257.98 | K13: -10557.71 | L13: 1395.61
D14: (e) Employee benefits expenses | H14: 6949.56 | I14: 7843.89 | J14: 10793.89 | K14: 9452.44 | L14: 8846.52
D15: (f) Finance costs | H15: 4261.32 | I15: 4353.84 | J15: 4859.52 | K15: 4440.26 | L15: 4843.39
D16: (g) Excise Duty on Goods Sold | H16: 16245.12 | I16: 16412.94 | J16: 14597.38 | K16: 12602.51 | L16: 7758.32
D17: (h) Depreciation and amortization expense | H17: 1242.62 | I17: 1148.05 | J17: 1807.97 | K17: 2908.21 | L17: 2750.21
D18: (i) Other expenses | H18: 2421.85 | I18: 3360.4 | J18: 4185.75 | K18: 4108.67 | L18: 3373.08
D19: Total expenses (IV) | H19: =SUM(H10:H18) -> 110522.87 | I19: =SUM(I10:I18) -> 125746.53 | J19: =SUM(J10:J18) -> 179818.02 | K19: =SUM(K10:K18) -> 128051.46 | L19: =SUM(L10:L18) -> 144291.67
D20: Profit/(loss) before exceptional items and tax from continuing operations | H20: 1860.13 | I20: 4636.84 | J20: 14839.24 | K20: 2980.14 | L20: -2211.11
D21: Exceptional Items | H21: 0 | I21: 0 | J21: 0 | K21: 0 | L21: 0
D22: Profit/(loss) before tax from continuing operations | H22: 1860.13 | I22: 4636.84 | J22: 14839.24 | K22: 2980.14 | L22: -2211.11
D23: Tax expense:
D24: Current tax | H24: 309.44 | I24: 1272.16 | J24: 3555.61 | K24: 793.96 | L24: 0
D25: MAT Credit entitlement for current year | H25: 0 | I25: -952.36 | J25: 0 | K25: 0 | L25: 0
D26: MAT Credit entitlement for earlier year | H26: 0 | I26: 0 | J26: 818.23 | K26: 0 | L26: 0
D27: Deferred tax | H27: -154.37 | I27: -15.8 | J27: 160.6 | K27: 71.93 | L27: -586.16
D28: Total Taxes (Net) | H28: =H24+H25+H26+H27 -> 155.07 | I28: =I24+I25+I26+I27 -> 304 | J28: =J24+J25+J26+J27 -> 4534.44 | K28: =K24+K25+K26+K27 -> 865.89 | L28: =L24+L25+L26+L27 -> -586.16
D29: Profit/(Loss) for the period | H29: =H22-SUM(H24:H27) -> 1705.06 | I29: =I22-SUM(I24:I27) -> 4332.84 | J29: =J22-SUM(J24:J27) -> 10304.8 | K29: =K22-SUM(K24:K27) -> 2114.25 | L29: =L22-SUM(L24:L27) -> -1624.95
A33: BALANCE SHEET | H33: =H4 -> 2021 | I33: =I4 -> 2022 | J33: =J4 -> 2023 | K33: =K4 -> 2024 | L33: =L4 -> 2025
B34: ASSETS
C35: Non-current Assets
D36: Tangible Assets:
D37: Property, plant and equipment | H37: 12833.05 | I37: 11867.63 | J37: 22356.39 | K37: 25365.01 | L37: 23390.18
D38: Capital work in progress | H38: 259.61 | I38: 11222.81 | J38: 3785.97 | K38: 7928.47 | L38: 14829.11
D39: Investment property | H39: 7.56 | I39: 7.12 | J39: 6.7 | K39: 6.33 | L39: 5.97
D40: Intangible Assets | H40: 0 | J40: 0 | K40: 0 | L40: 0
D41: Other Intangible assets | H41: 2.8 | I41: 2.52 | J41: 9.1 | K41: 7.65 | L41: 3.52
D42: Financial assets:
D43: Non - Current Investments | H43: 371.85 | I43: 366.97 | J43: 358.57 | K43: 353.57 | L43: 508.53
D44: Non - Current Loans & Advances | H44: 3.5 | I44: 3.5 | J44: 0 | K44: 0 | L44: 0
D45: Other non-current assets | H45: 326.1 | I45: 612.13 | J45: 1670.12 | K45: 1877.94 | L45: 1949.93
C46: Current Assets
D47: Inventories | H47: 63511.28 | I47: 76948.56 | J47: 36530.42 | K47: 48506.78 | L47: 52631.9
D48: Financial Assets:
D49: Trade receivables | H49: 4933.93 | I49: 8887.46 | J49: 18730.41 | K49: 14209.78 | L49: 12042.87
D50: Cash and cash equivalents | H50: 542.09 | I50: 624.26 | J50: 576.05 | K50: 93.84 | L50: 168.78
D51: Bank balances other than above | H51: 128.69 | I51: 146.39 | J51: 1260.95 | K51: 3968.06 | L51: 1724.5
D52: Other current financial assets | H52: 125.8 | I52: 145.01 | J52: 166.29 | K52: 330.02 | L52: 276.84
D53: Current Tax Assets (Net) | H53: 100.78 | I53: 231.49 | J53: 0 | K53: 0 | L53: 0
D54: Other current assets | H54: 6195.7 | I54: 5298.96 | J54: 6186.97 | K54: 5877.63 | L54: 5530.53
D55: Total Assets | H55: =SUM(H37:H54) -> 89342.74 | I55: =SUM(I37:I54) -> 116364.81 | J55: =SUM(J37:J54) -> 91637.94 | K55: =SUM(K37:K54) -> 108525.08 | L55: =SUM(L37:L54) -> 113062.66
B56: EQUITY AND LIABILITIES
C57: Equity
D58: Equity Share Capital | H58: 1125 | I58: 1125 | J58: 1125 | K58: 1125 | L58: 1125
D59: Other Equity:
D60: Share Premium | H60: 1575 | I60: 1575 | J60: 1575 | K60: 1575 | L60: 1575
D61: Retained Earnings | H61: 2969.45 | I61: 7077.33 | J61: 17100.87 | K61: 18652.62 | L61: 16746.45
D62: Other Reserves | H62: 2391.6 | I62: 2391.6 | J62: 2391.6 | K62: 2392.67 | L62: 2392.67
D63: Other Comprehensive Income | H63: -11.06 | I63: 7.31 | J63: -109.03 | K63: -248.48 | L63: -239.01
C64: Non-current Liabilities
D65: Financial Liabilities:
D66: Long Term Borrowings | H66: 7038.43 | I66: 12410.12 | J66: 14004.32 | K66: 8364.58 | L66: 9210.3
D67: Long Term Provisions | H67: 371.76 | I67: 364.41 | J67: 385.7 | K67: 343.88 | L67: 364.72
D68: Deferred tax liabilities (Net) | H68: 934.26 | I68: 926.76 | J68: 1046.99 | K68: 1070.92 | L68: 487.94
C69: Current Liabilities
D70: Financial Liabilities:
D71: Short Term Borrowings | H71: 48377.69 | I71: 51558.21 | J71: 20714.03 | K71: 43019.25 | L71: 51887.66
D72: Trade payables:
D73: Total outstanding dues of micro enterprises and small enterprises | H73: 19.66 | I73: 81.03 | J73: 575.79 | K73: 40.25 | L73: 122.97
D74: Total outstanding dues other than micro enterprises and small enterprises | H74: 11517.06 | I74: 22349.34 | J74: 14404.08 | K74: 16704.41 | L74: 11179.11
D75: Other payables | H75: 0 | I75: 0 | J75: 0 | K75: 0 | L75: 0
D76: Total outstanding dues of micro enterprises and small enterprises | H76: 0 | I76: 0 | J76: 0 | K76: 0 | L76: 0
D77: Total outstanding dues other than micro enterprises and small enterprises | H77: 213.09 | I77: 738.66 | J77: 631.79 | K77: 1756.21 | L77: 528.44
D78: Other financial liabilities | H78: 6398.2 | I78: 6922.74 | J78: 8461.35 | K78: 6806.59 | L78: 8515.71
D79: Provisions | H79: 1459.31 | I79: 1367.22 | J79: 1123.67 | K79: 1466.98 | L79: 1693.2
D80: Other current liabilities | H80: 4963.29 | I80: 7470.08 | J80: 5652.85 | K80: 4820.54 | L80: 7461.19
D81: Current Tax Liabilities (Net) | H81: 0 | I81: 0 | J81: 2553.93 | K81: 634.66 | L81: 11.31
D82: Total Lialibilities | H82: =SUM(H66:H81) -> 81292.75 | I82: =SUM(I66:I81) -> 104188.57 | J82: =SUM(J66:J81) -> 69554.5 | K82: =SUM(K66:K81) -> 85028.27 | L82: =SUM(L66:L81) -> 91462.55
D83: Total Lialibilities & Equity | H83: =SUM(H82,H58:H63) -> 89342.74 | I83: =SUM(I82,I58:I63) -> 116364.81 | J83: =SUM(J82,J58:J63) -> 91637.94 | K83: =SUM(K82,K58:K63) -> 108525.08 | L83: =SUM(L82,L58:L63) -> 113062.66
A87: CASHFLOW STATEMENT | H87: =H4 -> 2021 | I87: =I4 -> 2022 | J87: =J4 -> 2023 | K87: =K4 -> 2024 | L87: =L4 -> 2025
D88: Net profit before tax and extraordinary items | H88: 1860.13 | I88: 4636.84 | J88: 14839.24 | K88: 2980.14 | L88: -2211.11
D89: Adjustment for:
D90: Depreciation and amortization expense | H90: 1242.62 | I90: 1148.05 | J90: 1807.98 | K90: 2908.21 | L90: 2750.2
D91: Provision for Doubtful Debts, Bad Debts, & Sundry Advances Writen-off | H91: 6.03 | I91: 143.74 | J91: 53.53 | K91: 90.97 | L91: 21.63
D92: Bad debts and Sundry Advances Written off | H92: 21.67 | I92: 144.57 | J92: 9.23 | K92: 0.03 | L92: 0.02
D93: Loss/Gain on Disposal/Adjustment of PPE | H93: 15.49 | I93: 34.83 | J93: 0 | K93: 19.15 | L93: 1.36
D94: Finance Costs | H94: 4261.3 | I94: 4353.84 | J94: 4834.52 | K94: 4440.26 | L94: 4843.38
D95: Unrealised Loss on Units and Preference Shares | H95: 4.62 | I95: 7.31 | J95: 9.71 | K95: 10.85 | L95: -239.23
D96: Investment Income | H96: -67.94 | I96: -13.62 | J96: -25.64 | K96: -253.09 | L96: -176.89
D97: Operating profit before working capital changes | H97: =SUM(H88:H96) -> 7343.92 | I97: =SUM(I88:I96) -> 10455.56 | J97: =SUM(J88:J96) -> 21528.57 | K97: =SUM(K88:K96) -> 10196.52 | L97: =SUM(L88:L96) -> 4989.36
D98: Decrease/ (Increase) in trade receivables, advances and other assets | H98: -2975.16 | I98: -3703.61 | J98: -11675.45 | K98: 468.14 | L98: 3990.86
D99: Decrease/ (Increase) in Inventories | H99: -4734.61 | I99: -13437.27 | J99: 40418.14 | K99: -11976.36 | L99: -4125.13
D100: Increase/ (Decrease) in trade payables , provisions and other liabilities | H100: -7459.68 | I100: 16326.45 | J100: -7963.4 | K100: -524.52 | L100: -2690.39
D101: Cash Generated from operations | H101: =SUM(H97:H100) -> -7825.53 | I101: =SUM(I97:I100) -> 9641.13 | J101: =SUM(J97:J100) -> 42307.86 | K101: =SUM(K97:K100) -> -1836.22 | L101: =SUM(L97:L100) -> 2164.7
D102: Direct Tax paid (Net of Refund) | H102: 48.95 | I102: -340.97 | J102: -2903 | K102: -1895.58 | L102: -34.12
D103: Cash flow before extraordinary items | H103: =SUM(H101:H102) -> -7776.58 | I103: =SUM(I101:I102) -> 9300.16 | J103: =SUM(J101:J102) -> 39404.86 | K103: =SUM(K101:K102) -> -3731.8 | L103: =SUM(L101:L102) -> 2130.58
D104: Extraordinary items | H104: 0 | I104: 0 | J104: 0 | K104: 0 | L104: 0
C105: Net cash from Operating activities | H105: =SUM(H103:H104) -> -7776.58 | I105: =SUM(I103:I104) -> 9300.16 | J105: =SUM(J103:J104) -> 39404.86 | K105: =SUM(K103:K104) -> -3731.8 | L105: =SUM(L103:L104) -> 2130.58
D106: Cash flow from investing activities:
D107: Purchase of property, plant and equipment | H107: -610.92 | I107: -13154.35 | J107: -5923.88 | K107: -10284.52 | L107: -7744.83
...

Sheet Comps (Data)
A1: Company | B1: Ticker | C1: Stock Price | D1: Weighted Avg. Shares Outstanding Dil | E1: Market Cap | F1: Total Debt | G1: Cash And Equivalents & Short term investments | H1: Total Revenues | I1: EBITDA | J1: Net Income (Income Statement) | K1: Effective Tax Rate | L1: Revenue 10Y CAGR | M1: Revenue 5Y CAGR | N1: Short-term Borrowings
A2: Mawana Sugars Limited | B2: 523371 | C2: 79.5 | D2: 390.99666 | E2: 31097.907 | F2: 19559.408 | G2: 1521.7 | H2: 152953.44 | I2: 12085.844 | J2: 10172.867 | K2: 0.164934 | M2: 0.029027 | N2: 6199.5331
A3: DCM Shriram Industries Limited | B3: 523369 | C3: 37.59 | D3: 869.54098 | E3: 32700.362 | F3: 57177.206 | G3: 11028.9 | H3: 213747.05 | I3: 18989.116 | J3: 9313.5687 | K3: 0.354496 | L3: 0.046803 | M3: 0.021199 | N3: 4822.6084
A4: Magadh Sugar & Energy Limited | B4: MAGADSUGAR | C4: 417.8 | D4: 140.44682 | E4: 58874.83 | F4: 75737.668 | G4: 133.5 | H4: 138761.06 | I4: 20908.76 | J4: 10519.333 | K4: 0.256562 | M4: 0.068992 | N4: 5140.6163
A5: Dwarikesh Sugar Industries Limited | B5: 532610 | C5: 33.33 | D5: 1846.9899 | E5: 61760.98 | F5: 54311.716 | G5: 29261.02 | H5: 152377.14 | I5: 11954.825 | J5: 2535.2519 | K5: 0.564909 | L5: 0.088695 | M5: 0.003634 | N5: 3824.8669
A6: Avadh Sugar & Energy Limited | B6: AVADHSUGAR | C6: 322.35 | D6: 200.22026 | E6: 64529.377 | F6: 146798.27 | G6: 372.8 | H6: 283126.79 | I6: 26403.179 | J6: 7584.426 | K6: 0.35483 | M6: -2.4e-05 | N6: 10580.313
A7: Davangere Sugar Company Limited | B7: DAVANGERE | C7: 4.59 | D7: 7290.8429 | E7: 46392.038 | F7: 38172.128 | G7: 1220.1 | H7: 20717.142 | I7: 5768.9815 | J7: 1210.0573 | K7: 0.145261 | L7: 0.020181 | M7: 0.022582 | N7: 2109.233
A8: Dhampur Sugar Mills Limited | B8: 500119 | C8: 113.2 | D8: 652.05772 | E8: 72794.968 | F8: 100215.12 | G8: 25153.076 | H8: 211870.06 | I8: 17567.145 | J8: 5514.3263 | K8: 0.302683 | L8: 0.003379 | M8: -0.114763 | N8: 7522.4878
A9: Uttam Sugar Mills Limited | B9: 532729 | C9: 208.7 | D9: 381.55192 | E9: 79594.256 | F9: 28639.377 | G9: 2093.5 | H9: 227501.8 | I9: 25616.294 | J9: 11632.761 | K9: 0.265864 | L9: 0.110827 | M9: 0.039236 | N9: 7809.5786
A11: The Ugar Sugar Works Limited | B11: 530363 | C11: =Assumptions!E11 -> 39.33 | D11: 1125.3063 | E11: =C11*D11 -> 44258.298 | F11: 45440.079 | G11: 1916.7361 | H11: 159888.72 | I11: 7657.5538 | J11: 1002.5592 | K11: =AVERAGE('Ratio Analysis & Interpretation'!M13:Q13) -> 0.27409762 | L11: 0.131631 | M11: 0.117959 | N11: 3659.7222
D13: The date was in INR Million so converted it into INR Lakhs | G13: 10
A16: Back to Cover

Sheet Assumptions (Data)
A1: ='Historical Info'!A1 -> Ugar Sugar Works Ltd.
A2: Revenue growth Assumption- Data (Values are in INR Lakhs)
D4: Assumptions for Revenue Growth (Base Case Scenario)
D5: Segment wise Revenue contribution- FY-2025
D6: Segment & Product | E6: Revenue | F6: Weightage in Rev. | G6: Industry Growth Rate
D7: i. SUGAR | E7: 53334.21 | F7: =E7/E18 -> 0.37911086 | G7: 0.1
D8: ii. DISTILLERY | F8: {=SUM(E9:E12/E18)} -> 0.50015446 | G8: 0.1
D9: a. Rectified Spirit | E9: 26.7
D10: b. Denatured Spirit | E10: 0
D11: c. Potable Alcohol | E11: 9147.59
D12: d. Biofuel | E12: 61188.62
D13: iii. OTHERS | F13: {=SUM(E14:E17/E18)} -> 0.12073468 | G13: =F41 -> 0.088733243
D14: a. Electricity | E14: 2144.41
D15: b. Petroleum Products | E15: 4130.01
D16: c. Broken Rice | E16: 0
D17: d. By-Products & Others | E17: 10710.82
D18: Total | E18: =SUM(E7:E17) -> 140682.36 | F18: =E18/E18 -> 1 | G18: =(F7*G7)+(F8*G8)+(F13*G13) -> 0.098639712 | H18: (Weighted-average revenue growth rate: base case)
D20: Factors that I considered to make segment wise industry growth rate assumptions
C21: i. Sugar
D22: India’s sugar production increased by 58% over the past decade, reflecting a long-term CAGR of around 4.7%, representing the steady but moderate structural growth.
D23: Based on CRISIL Ratings reports as of June 2025, "India's gross sugar production is expected to rise by approximately 15% in the 2025-26 season to around 35 million tonnes."
D24: Sugar is expected to see 15% growth in FY 2025-26, so will take 10% average growth rate
C25: ii. Distillery
D26: Ugar Sugar is clearly prioritizing and strengthening its distillery business alongside sugar, because distillery offers higher margins, more stable demand, and policy-driven growth visibility.
D27: India achieves 20% ethanol blending target- ISMA IBEF July 28, 2025
D28: Ethanol production grew from 380 million litres (2014) to 6,610 million litres (2025)
D29: This is a 17.4× increase over 11 years
D30: It gave the CAGR of 29.6% over the last 11 years
D31: Since India has achieved the 20% Ethanol Blending target so now its in Maturity phase
D32: The optimum growth of Distillery would be: 8-12%
C34: iii. OTHERS | E34: 2021 | F34: =E34+1 -> 2022 | G34: =F34+1 -> 2023 | H34: =G34+1 -> 2024 | I34: =H34+1 -> 2025
D35: a. Electricity | E35: 4437.75 | F35: 4866.03 | G35: 4920.06 | H35: 3629.41 | I35: 2144.41
D36: b. Petroleum Products | E36: 4065.69 | F36: 4769.59 | G36: 4839.69 | H36: 4206.24 | I36: 4130.01
D37: c. Broken Rice | E37: 0 | F37: 0 | G37: 0 | H37: 842.74 | I37: 0
D38: d. By-Products & Others | E38: 3673.99 | F38: 3500.89 | G38: 6072.86 | H38: 8717.02 | I38: 10710.8
D39: Total Revenue of Other products | E39: =SUM(E35:E38) -> 12177.43 | F39: =SUM(F35:F38) -> 13136.51 | G39: =SUM(G35:G38) -> 15832.61 | H39: =SUM(H35:H38) -> 17395.41 | I39: =SUM(I35:I38) -> 16985.22
D40: Historical Growth rate | F40: =F39/E39-1 -> 0.078758819 | G40: =G39/F39-1 -> 0.20523716 | H40: =H39/G39-1 -> 0.098707667 | I40: =I39/H39-1 -> -0.023580358
D41: OTHERS Median growth rate | F41: =MEDIAN(F40:I40) -> 0.088733243
D44: Other Assumptions
C45: 1 | D45: the depreciation rate grows once every 3 years by 2%. % does not change.
C46: 2 | D46: The Effective Tax Rate increases by 0.5-1% every 2 years, (However, if tax reaches 30%, stop it there.)
C47: 3 | D47: After averaging the Capex, We assume that it will grow by .5% Every year & we are allocating the adjusted capex into the assets in the proportion of latest audited year.
C48: 4 | D48: For the Forecasting of Tax rate, we are not averaging but taking the last audited year's % and then assuming it will grow by .5% in every 2 years
C49: 5 | D49: All the remaining costs and other line items's forecast is dependent upon the revenue growth.
D52: Back to Cover

Sheet Working Schedules
A1: ='Historical Info'!A1 -> Ugar Sugar Works Ltd.
A2: Revenue Growth Scenarios
A4: Supporting Schedules | H4: ='Financial Statements'!H2 -> 2021 | I4: ='Financial Statements'!I2 -> 2022 | J4: ='Financial Statements'!J2 -> 2023 | K4: ='Financial Statements'!K2 -> 2024 | L4: ='Financial Statements'!L2 -> 2025 | M4: ='Financial Statements'!M2 -> 2026 | N4: ='Financial Statements'!N2 -> 2027 | O4: ='Financial Statements'!O2 -> 2028 | ... V4: ='Financial Statements'!V2 -> 2035
C6: Working Capital Schedule | F6: ='Financial Statements'!F61 -> ₹ in Lakhs
D7: Accounts Receivables | H7: ='Historical Info'!H98 -> -2975.16 | I7: ='Historical Info'!I98 -> -3703.61 | J7: ='Historical Info'!J98 -> -11675.45 | K7: ='Historical Info'!K98 -> 468.14 | L7: ='Historical Info'!L98 -> 3990.86 | M7: ='Financial Statements'!L31-'Financial Statements'!M31 -> -505.70939 | N7: ='Financial Statements'!M31-'Financial Statements'!N31 -> -1120.1984 | O7: ='Financial Statements'!N31-'Financial Statements'!O31 -> -1104.2785 | P7: ='Financial Statements'!O31-'Financial Statements'!P31 -> -1080.1097 | Q7: ='Financial Statements'!P31-'Financial Statements'!Q31 -> -1048.9677 | R7: ='Financial Statements'!Q31-'Financial Statements'!R31 -> -1012.1298 | S7: ='Financial Statements'!R31-'Financial Statements'!S31 -> -970.82786 | T7: ='Financial Statements'!S31-'Financial Statements'!T31 -> -926.21315 | ... V7: ='Financial Statements'!U31-'Financial Statements'!V31 -> -831.11838
D8: Inventory | H8: ='Historical Info'!H99 -> -4734.61 | I8: ='Historical Info'!I99 -> -13437.27 | J8: ='Historical Info'!J99 -> 40418.14 | K8: ='Historical Info'!K99 -> -11976.36 | L8: ='Historical Info'!L99 -> -4125.13 | M8: ='Financial Statements'!L32-'Financial Statements'!M32 -> -13120.15 | N8: ='Financial Statements'!M32-'Financial Statements'!N32 -> -5869.6157 | O8: ='Financial Statements'!N32-'Financial Statements'!O32 -> -5786.1991 | P8: ='Financial Statements'!O32-'Financial Statements'!P32 -> -5659.5594 | Q8: ='Financial Statements'!P32-'Financial Statements'!Q32 -> -5496.3813 | R8: ='Financial Statements'!Q32-'Financial Statements'!R32 -> -5303.3582 | S8: ='Financial Statements'!R32-'Financial Statements'!S32 -> -5086.9441 | T8: ='Financial Statements'!S32-'Financial Statements'!T32 -> -4853.1719 | ... V8: ='Financial Statements'!U32-'Financial Statements'!V32 -> -4354.8943
D9: Accounts Payables | H9: ='Historical Info'!H100 -> -7459.68 | I9: ='Historical Info'!I100 -> 16326.45 | J9: ='Historical Info'!J100 -> -7963.4 | K9: ='Historical Info'!K100 -> -524.52 | L9: ='Historical Info'!L100 -> -2690.39 | M9: ='Financial Statements'!M44-'Financial Statements'!L44 -> 6722.3627 | N9: ='Financial Statements'!N44-'Financial Statements'!M44 -> 1656.1962 | O9: ='Financial Statements'!O44-'Financial Statements'!N44 -> 1632.6589 | P9: ='Financial Statements'!P44-'Financial Statements'!O44 -> 1596.9257 | Q9: ='Financial Statements'!Q44-'Financial Statements'!P44 -> 1550.8827 | R9: ='Financial Statements'!R44-'Financial Statements'!Q44 -> 1496.4185 | S9: ='Financial Statements'!S44-'Financial Statements'!R44 -> 1435.3541 | T9: ='Financial Statements'!T44-'Financial Statements'!S44 -> 1369.392 | ... V9: ='Financial Statements'!V44-'Financial Statements'!U44 -> 1228.7958
D10: Other | H10: 0 | I10: 0 | J10: 0 | K10: 0 | L10: 0 | M10: =('Financial Statements'!L33-'Financial Statements'!M33)+('Financial Statements'!M45-'Financial Statements'!L45) -> 0 | N10: =('Financial Statements'!M33-'Financial Statements'!N33)+('Financial Statements'!N45-'Financial Statements'!M45) -> 0 | O10: =('Financial Statements'!N33-'Financial Statements'!O33)+('Financial Statements'!O45-'Financial Statements'!N45) -> 0 | P10: =('Financial Statements'!O33-'Financial Statements'!P33)+('Financial Statements'!P45-'Financial Statements'!O45) -> 0 | Q10: =('Financial Statements'!P33-'Financial Statements'!Q33)+('Financial Statements'!Q45-'Financial Statements'!P45) -> 0 | R10: =('Financial Statements'!Q33-'Financial Statements'!R33)+('Financial Statements'!R45-'Financial Statements'!Q45) -> 0 | S10: =('Financial Statements'!R33-'Financial Statements'!S33)+('Financial Statements'!S45-'Financial Statements'!R45) -> 0 | T10: =('Financial Statements'!S33-'Financial Statements'!T33)+('Financial Statements'!T45-'Financial Statements'!S45) -> 0 | ... V10: =('Financial Statements'!U33-'Financial Statements'!V33)+('Financial Statements'!V45-'Financial Statements'!U45) -> 0
D11: Total | H11: =SUM(H7:H10) -> -15169.45 | I11: =SUM(I7:I10) -> -814.43 | J11: =SUM(J7:J10) -> 20779.29 | K11: =SUM(K7:K10) -> -12032.74 | L11: =SUM(L7:L10) -> -2824.66 | M11: =SUM(M7:M10) -> -6903.4966 | N11: =SUM(N7:N10) -> -5333.618 | O11: =SUM(O7:O10) -> -5257.8187 | ... V11: =SUM(V7:V10) -> -3957.2169
C13: Depreciation Schedule
D14: PP&E Opening balance | I14: =H17 -> 13092.66 | J14: =I17 -> 23090.44 | K14: =J17 -> 26142.36 | L14: =K17 -> 33293.48 | M14: =L17 -> 38219.29 | N14: =M17 -> 43497.451 | O14: =N17 -> 48381.785 | P14: =O17 -> 51937.4 | ... V14: =U17 -> 62170.087
D15: Plus: Capex | I15: =I17-I14-I16 -> 11145.83 | J15: =J17-J14-J16 -> 4859.9 | K15: =K17-K14-K16 -> 10059.33 | L15: =L17-L14-L16 -> 7676.01 | M15: =AVERAGE(I15:L15) -> 8435.2675 | N15: =M15*(1+0.5%) -> 8477.4438 | O15: =N15*(1+0.5%) -> 8519.8311 | P15: =O15*(1+0.5%) -> 8562.4302 | Q15: =P15*(1+0.5%) -> 8605.2424 | R15: =Q15*(1+0.5%) -> 8648.2686 | S15: =R15*(1+0.5%) -> 8691.5099 | T15: =S15*(1+0.5%) -> 8734.9675 | U15: =T15*(1+0.5%) -> 8778.6423 | V15: =U15*(1+0.5%) -> 8822.5355
D16: Less: Depreciation | H16: =-'Financial Statements'!H62 -> -1242.62 | I16: =-'Financial Statements'!I62 -> -1148.05 | J16: =-'Financial Statements'!J62 -> -1807.98 | K16: =-'Financial Statements'!K62 -> -2908.21 | L16: =-'Financial Statements'!L62 -> -2750.2 | M16: =-M14*'Ratio Analysis & Interpretation'!M10 -> -3157.1068 | N16: =-N14*'Ratio Analysis & Interpretation'!N10 -> -3593.1096 | O16: =-O14*'Ratio Analysis & Interpretation'!O10 -> -4964.2161 | P16: =-P14*'Ratio Analysis & Interpretation'!P10 -> -5329.0402 | Q16: =-Q14*'Ratio Analysis & Interpretation'!Q10 -> -5660.8024 | R16: =-R14*'Ratio Analysis & Interpretation'!R10 -> -7125.2214 | S16: =-S14*'Ratio Analysis & Interpretation'!S10 -> -7311.9547 | T16: =-T14*'Ratio Analysis & Interpretation'!T10 -> -7481.0952 | ... V16: =-V14*'Ratio Analysis & Interpretation'!V10 -> -8865.7691
D17: PP&E Closing Balance | H17: ='Financial Statements'!H36 -> 13092.66 | I17: ='Financial Statements'!I36 -> 23090.44 | J17: ='Financial Statements'!J36 -> 26142.36 | K17: ='Financial Statements'!K36 -> 33293.48 | L17: ='Financial Statements'!L36 -> 38219.29 | M17: =SUM(M14:M16) -> 43497.451 | N17: =SUM(N14:N16) -> 48381.785 | O17: =SUM(O14:O16) -> 51937.4 | P17: =SUM(P14:P16) -> 55170.79 | Q17: =SUM(Q14:Q16) -> 58115.23 | R17: =SUM(R14:R16) -> 59638.277 | S17: =SUM(S14:S16) -> 61017.832 | T17: =SUM(T14:T16) -> 62271.705 | ... V17: =SUM(V14:V16) -> 62126.853
C19: Debt and Interest Schedule
D20: Debt Opening Balance | I20: =H22 -> 55416.12 | J20: =I22 -> 63968.33 | K20: =J22 -> 34718.35 | L20: =K22 -> 51383.83 | M20: =L22 -> 61097.96 | N20: =M22 -> 61097.96 | O20: =N22 -> 61097.96 | P20: =O22 -> 61097.96 | ... V20: =U22 -> 61097.96
D21: Issuance (Repayment) of Debt | I21: =I22-I20 -> 8552.21 | J21: =J22-J20 -> -29249.98 | K21: =K22-K20 -> 16665.48 | L21: =L22-L20 -> 9714.13 | M21: 0 | N21: 0 | O21: 0 | P21: 0 | Q21: 0 | R21: 0 | S21: 0 | T21: 0 | U21: 0 | V21: 0
D22: Debt Closing Balance | H22: ='Financial Statements'!H47 -> 55416.12 | I22: ='Financial Statements'!I47 -> 63968.33 | J22: ='Financial Statements'!J47 -> 34718.35 | K22: ='Financial Statements'!K47 -> 51383.83 | L22: ='Financial Statements'!L47 -> 61097.96 | M22: =SUM(M20:M21) -> 61097.96 | N22: =SUM(N20:N21) -> 61097.96 | O22: =SUM(O20:O21) -> 61097.96 | P22: =SUM(P20:P21) -> 61097.96 | Q22: =SUM(Q20:Q21) -> 61097.96 | R22: =SUM(R20:R21) -> 61097.96 | S22: =SUM(S20:S21) -> 61097.96 | T22: =SUM(T20:T21) -> 61097.96 | ... V22: =SUM(V20:V21) -> 61097.96
D23: Interest Expense | H23: ='Financial Statements'!H19 -> -4261.32 | I23: ='Financial Statements'!I19 -> -4353.84 | J23: ='Financial Statements'!J19 -> -4859.52 | K23: ='Financial Statements'!K19 -> -4440.26 | L23: ='Financial Statements'!L19 -> -4843.39 | M23: =-M22*'Ratio Analysis & Interpretation'!M11 -> -5753.697 | N23: =-N22*'Ratio Analysis & Interpretation'!N11 -> -5753.697 | O23: =-O22*'Ratio Analysis & Interpretation'!O11 -> -5753.697 | P23: =-P22*'Ratio Analysis & Interpretation'!P11 -> -5753.697 | Q23: =-Q22*'Ratio Analysis & Interpretation'!Q11 -> -5753.697 | R23: =-R22*'Ratio Analysis & Interpretation'!R11 -> -5753.697 | S23: =-S22*'Ratio Analysis & Interpretation'!S11 -> -5753.697 | T23: =-T22*'Ratio Analysis & Interpretation'!T11 -> -5753.697 | ... V23: =-V22*'Ratio Analysis & Interpretation'!V11 -> -5753.697

Sheet Financial Statements
A1: ='Historical Info'!A1 -> Ugar Sugar Works Ltd. | H1: Historical Info. | M1: Forecasted Info. | Y1: Interpretation of Ratios
A2: Financial Statements and DCF Analysis | H2: 2021 | I2: =H2+1 -> 2022 | J2: =I2+1 -> 2023 | K2: =J2+1 -> 2024 | L2: =K2+1 -> 2025 | M2: =L2+1 -> 2026 | N2: =M2+1 -> 2027 | O2: =N2+1 -> 2028 | P2: =O2+1 -> 2029 | ... V2: =U2+1 -> 2035 | W2: Trend
D3: Master Check | H3: =IF(H57="Perfect","Perfect","Error") -> Perfect | I3: =IF(I57="Perfect","Perfect","Error") -> Perfect | J3: =IF(J57="Perfect","Perfect","Error") -> Perfect | K3: =IF(K57="Perfect","Perfect","Error") -> Perfect | L3: =IF(L57="Perfect","Perfect","Error") -> Perfect | M3: =IF(M57="Perfect","Perfect","Error") -> Perfect | N3: =IF(N57="Perfect","Perfect","Error") -> Perfect | O3: =IF(O57="Perfect","Perfect","Error") -> Perfect | ... V3: =IF(V57="Perfect","Perfect","Error") -> Perfect
D6: LIVE SCENARIO | E6: Base Case | F6: Units | G6: =IF(E6='Rev Growth Scenarios'!D5,1,IF('Financial Statements'!E6='Rev Growth Scenarios'!D6,2,3)) -> 1
A8: Income Statement
B9: INCOME
D10: Revenue | F10: ₹ in Lakhs | H10: ='Historical Info'!H6 -> 111796.48 | I10: ='Historical Info'!I6 -> 130158.9 | J10: ='Historical Info'!J6 -> 194014.95 | K10: ='Historical Info'!K6 -> 127723.66 | L10: ='Historical Info'!L6 -> 140741.27 | M10: =L10*(1+'Ratio Analysis & Interpretation'!M6) -> 154623.95 | N10: =M10*(1+'Ratio Analysis & Interpretation'!N6) -> 168427.06 | O10: =N10*(1+'Ratio Analysis & Interpretation'!O6) -> 182034.02 | P10: =O10*(1+'Ratio Analysis & Interpretation'!P6) -> 195343.16 | Q10: =P10*(1+'Ratio Analysis & Interpretation'!Q6) -> 208268.57 | R10: =Q10*(1+'Ratio Analysis & Interpretation'!R6) -> 220740.06 | S10: =R10*(1+'Ratio Analysis & Interpretation'!S6) -> 232702.63 | T10: =S10*(1+'Ratio Analysis & Interpretation'!T6) -> 244115.45 | ... V10: =U10*(1+'Ratio Analysis & Interpretation'!V6) -> 265191.69
D11: COGS | H11: =-('Historical Info'!H10+'Historical Info'!H11+'Historical Info'!H12+'Historical Info'!H13) -> -79402.4 | I11: =-('Historical Info'!I10+'Historical Info'!I11+'Historical Info'!I12+'Historical Info'!I13) -> -92627.41 | J11: =-('Historical Info'!J10+'Historical Info'!J11+'Historical Info'!J12+'Historical Info'!J13) -> -143573.51 | K11: =-('Historical Info'!K10+'Historical Info'!K11+'Historical Info'!K12+'Historical Info'!K13) -> -94539.37 | L11: =-('Historical Info'!L10+'Historical Info'!L11+'Historical Info'!L12+'Historical Info'!L13) -> -116720.15 | M11: =-M10*'Ratio Analysis & Interpretation'!M7 -> -115393.16 | N11: =-N10*'Ratio Analysis & Interpretation'!N7 -> -125694.19 | O11: =-O10*'Ratio Analysis & Interpretation'!O7 -> -135848.82 | P11: =-P10*'Ratio Analysis & Interpretation'!P7 -> -145781.2 | Q11: =-Q10*'Ratio Analysis & Interpretation'!Q7 -> -155427.21 | R11: =-R10*'Ratio Analysis & Interpretation'!R7 -> -164734.47 | S11: =-S10*'Ratio Analysis & Interpretation'!S7 -> -173661.92 | T11: =-T10*'Ratio Analysis & Interpretation'!T7 -> -182179.11 | ... V11: =-V10*'Ratio Analysis & Interpretation'!V7 -> -197907.94
D12: Gross Profit | H12: =SUM(H10:H11) -> 32394.08 | I12: =SUM(I10:I11) -> 37531.49 | J12: =SUM(J10:J11) -> 50441.44 | K12: =SUM(K10:K11) -> 33184.29 | L12: =SUM(L10:L11) -> 24021.12 | M12: =SUM(M10:M11) -> 39230.786 | N12: =SUM(N10:N11) -> 42732.877 | O12: =SUM(O10:O11) -> 46185.197 | ... V12: =SUM(V10:V11) -> 67283.746
B13: EXPENSES
D14: Salaries & benefits | H14: =-'Historical Info'!H14 -> -6949.56 | I14: =-'Historical Info'!I14 -> -7843.89 | J14: =-'Historical Info'!J14 -> -10793.89 | K14: =-'Historical Info'!K14 -> -9452.44 | L14: =-'Historical Info'!L14 -> -8846.52 | M14: =-M10*'Ratio Analysis & Interpretation'!M8 -> -9738.9725 | N14: =-N10*'Ratio Analysis & Interpretation'!N8 -> -10608.36 | O14: =-O10*'Ratio Analysis & Interpretation'!O8 -> -11465.393 | P14: =-P10*'Ratio Analysis & Interpretation'!P8 -> -12303.667 | Q14: =-Q10*'Ratio Analysis & Interpretation'!Q8 -> -13117.773 | R14: =-R10*'Ratio Analysis & Interpretation'!R8 -> -13903.289 | S14: =-S10*'Ratio Analysis & Interpretation'!S8 -> -14656.75 | T14: =-T10*'Ratio Analysis & Interpretation'!T8 -> -15375.585 | ... V14: =-V10*'Ratio Analysis & Interpretation'!V8 -> -16703.069
D15: Other SG&A expenses | H15: =-('Historical Info'!H16+'Historical Info'!H18) -> -18666.97 | I15: =-('Historical Info'!I16+'Historical Info'!I18) -> -19773.34 | J15: =-('Historical Info'!J16+'Historical Info'!J18) -> -18783.13 | K15: =-('Historical Info'!K16+'Historical Info'!K18) -> -16711.18 | L15: =-('Historical Info'!L16+'Historical Info'!L18) -> -11131.4 | M15: =-M10*'Ratio Analysis & Interpretation'!M9 -> -19347.547 | N15: =-N10*'Ratio Analysis & Interpretation'!N9 -> -21074.682 | O15: =-O10*'Ratio Analysis & Interpretation'!O9 -> -22777.272 | P15: =-P10*'Ratio Analysis & Interpretation'!P9 -> -24442.598 | Q15: =-Q10*'Ratio Analysis & Interpretation'!Q9 -> -26059.909 | R15: =-R10*'Ratio Analysis & Interpretation'!R9 -> -27620.422 | S15: =-S10*'Ratio Analysis & Interpretation'!S9 -> -29117.256 | T15: =-T10*'Ratio Analysis & Interpretation'!T9 -> -30545.303 | ... V15: =-V10*'Ratio Analysis & Interpretation'!V9 -> -33182.497 | Y15: Other SG&A expenses
D16: EBITDA | H16: =SUM(H12,H14:H15) -> 6777.55 | I16: =SUM(I12,I14:I15) -> 9914.26 | J16: =SUM(J12,J14:J15) -> 20864.42 | K16: =SUM(K12,K14:K15) -> 7020.67 | L16: =SUM(L12,L14:L15) -> 4043.2 | M16: =SUM(M12,M14:M15) -> 10144.267 | N16: =SUM(N12,N14:N15) -> 11049.834 | O16: =SUM(O12,O14:O15) -> 11942.533 | ... V16: =SUM(V12,V14:V15) -> 17398.179 | Y16: Depreciation & Amortization expenses
D17: Depreciation & Amortization expenses | H17: =-'Historical Info'!H17 -> -1242.62 | I17: =-'Historical Info'!I17 -> -1148.05 | J17: =-'Historical Info'!J17 -> -1807.97 | K17: =-'Historical Info'!K17 -> -2908.21 | L17: =-'Historical Info'!L17 -> -2750.21 | M17: ='Working Schedules'!M16 -> -3157.1068 | N17: ='Working Schedules'!N16 -> -3593.1096 | O17: ='Working Schedules'!O16 -> -4964.2161 | P17: ='Working Schedules'!P16 -> -5329.0402 | Q17: ='Working Schedules'!Q16 -> -5660.8024 | R17: ='Working Schedules'!R16 -> -7125.2214 | S17: ='Working Schedules'!S16 -> -7311.9547 | T17: ='Working Schedules'!T16 -> -7481.0952 | ... V17: ='Working Schedules'!V16 -> -8865.7691 | Y17: Interest
D18: EBIT | H18: =SUM(H16:H17) -> 5534.93 | I18: =SUM(I16:I17) -> 8766.21 | J18: =SUM(J16:J17) -> 19056.45 | K18: =SUM(K16:K17) -> 4112.46 | L18: =SUM(L16:L17) -> 1292.99 | M18: =SUM(M16:M17) -> 6987.1597 | N18: =SUM(N16:N17) -> 7456.7248 | O18: =SUM(O16:O17) -> 6978.3167 | ... V18: =SUM(V16:V17) -> 8532.41 | Y18: Other Income (Expenses)
D19: Interest | H19: =-'Historical Info'!H15 -> -4261.32 | I19: =-'Historical Info'!I15 -> -4353.84 | J19: =-'Historical Info'!J15 -> -4859.52 | K19: =-'Historical Info'!K15 -> -4440.26 | L19: =-'Historical Info'!L15 -> -4843.39 | M19: ='Working Schedules'!M23 -> -5753.697 | N19: ='Working Schedules'!N23 -> -5753.697 | O19: ='Working Schedules'!O23 -> -5753.697 | P19: ='Working Schedules'!P23 -> -5753.697 | Q19: ='Working Schedules'!Q23 -> -5753.697 | R19: ='Working Schedules'!R23 -> -5753.697 | S19: ='Working Schedules'!S23 -> -5753.697 | T19: ='Working Schedules'!T23 -> -5753.697 | ... V19: ='Working Schedules'!V23 -> -5753.697 | Y19: Taxes
D20: Other Income (Expenses) | H20: ='Historical Info'!H7 -> 586.52 | I20: ='Historical Info'!I7 -> 224.47 | J20: ='Historical Info'!J7 -> 642.31 | K20: ='Historical Info'!K7 -> 3307.94 | L20: ='Historical Info'!L7 -> 1339.29 | M20: =M10*'Ratio Analysis & Interpretation'!M12 -> 1413.1606 | N20: =N10*'Ratio Analysis & Interpretation'!N12 -> 1539.3119 | O20: =O10*'Ratio Analysis & Interpretation'!O12 -> 1663.6705 | P20: =P10*'Ratio Analysis & Interpretation'!P12 -> 1785.3072 | Q20: =Q10*'Ratio Analysis & Interpretation'!Q12 -> 1903.4369 | R20: =R10*'Ratio Analysis & Interpretation'!R12 -> 2017.4181 | S20: =S10*'Ratio Analysis & Interpretation'!S12 -> 2126.7481 | T20: =T10*'Ratio Analysis & Interpretation'!T12 -> 2231.0537 | ... V20: =V10*'Ratio Analysis & Interpretation'!V12 -> 2423.6765
D21: Earnings before Tax | H21: =SUM(H18:H20) -> 1860.13 | I21: =SUM(I18:I20) -> 4636.84 | J21: =SUM(J18:J20) -> 14839.24 | K21: =SUM(K18:K20) -> 2980.14 | L21: =SUM(L18:L20) -> -2211.11 | M21: =SUM(M18:M20) -> 2646.6233 | N21: =SUM(N18:N20) -> 3242.3398 | O21: =SUM(O18:O20) -> 2888.2902 | ... V21: =SUM(V18:V20) -> 5202.3896
D22: Taxes | H22: =-'Historical Info'!H28 -> -155.07 | I22: =-'Historical Info'!I28 -> -304 | J22: =-'Historical Info'!J28 -> -4534.44 | K22: =-'Historical Info'!K28 -> -865.89 | L22: =-'Historical Info'!L28 -> 586.16 | M22: =-M21*'Ratio Analysis & Interpretation'!M13 -> -714.84667 | N22: =-N21*'Ratio Analysis & Interpretation'!N13 -> -875.74827 | O22: =-O21*'Ratio Analysis & Interpretation'!O13 -> -794.56177 | P22: =-P21*'Ratio Analysis & Interpretation'!P13 -> -967.86583 | Q22: =-Q21*'Ratio Analysis & Interpretation'!Q13 -> -1163.1378 | R22: =-R21*'Ratio Analysis & Interpretation'!R13 -> -1014.0607 | S22: =-S21*'Ratio Analysis & Interpretation'!S13 -> -1233.8446 | T22: =-T21*'Ratio Analysis & Interpretation'!T13 -> -1428.8273 | ... V22: =-V21*'Ratio Analysis & Interpretation'!V13 -> -1509.2009
D23: Net Earnings (PAT) | H23: =SUM(H21:H22) -> 1705.06 | I23: =SUM(I21:I22) -> 4332.84 | J23: =SUM(J21:J22) -> 10304.8 | K23: =SUM(K21:K22) -> 2114.25 | L23: =SUM(L21:L22) -> -1624.95 | M23: =SUM(M21:M22) -> 1931.7767 | N23: =SUM(N21:N22) -> 2366.5915 | O23: =SUM(O21:O22) -> 2093.7285 | ... V23: =SUM(V21:V22) -> 3693.1888
A26: Balance Sheet
B27: ASSETS
C28: Current Assets | F28: =F10 -> ₹ in Lakhs
D29: Cash | H29: ='Historical Info'!H50 -> 542.09 | I29: ='Historical Info'!I50 -> 624.26 | J29: ='Historical Info'!J50 -> 576.05 | K29: ='Historical Info'!K50 -> 93.84 | L29: ='Historical Info'!L50 -> 168.78 | M29: =M84 -> -10279.713 | N29: =N84 -> -18374.392 | O29: =O84 -> -25309.36 | P29: =P84 -> -31397.312 | Q29: =Q84 -> -36654.099 | R29: =R84 -> -40657.858 | S29: =S84 -> -43883.979 | T29: =T84 -> -46333.328 | ... V29: =V84 -> -48202.289
D30: Bank Deposits | H30: ='Historical Info'!H51 -> 128.69 | I30: ='Historical Info'!I51 -> 146.39 | J30: ='Historical Info'!J51 -> 1260.95 | K30: ='Historical Info'!K51 -> 3968.06 | L30: ='Historical Info'!L51 -> 1724.5 | M30: =L30 -> 1724.5 | N30: =M30 -> 1724.5 | O30: =N30 -> 1724.5 | P30: =O30 -> 1724.5 | Q30: =P30 -> 1724.5 | R30: =Q30 -> 1724.5 | S30: =R30 -> 1724.5 | T30: =S30 -> 1724.5 | ... V30: =U30 -> 1724.5
D31: Account Receivables | H31: ='Historical Info'!H49 -> 4933.93 | I31: ='Historical Info'!I49 -> 8887.46 | J31: ='Historical Info'!J49 -> 18730.41 | K31: ='Historical Info'!K49 -> 14209.78 | L31: ='Historical Info'!L49 -> 12042.87 | M31: =(M10*'Ratio Analysis & Interpretation'!M15)/365 -> 12548.579 | N31: =N10*'Ratio Analysis & Interpretation'!N15/365 -> 13668.778 | O31: =O10*'Ratio Analysis & Interpretation'!O15/365 -> 14773.056 | P31: =P10*'Ratio Analysis & Interpretation'!P15/365 -> 15853.166 | Q31: =Q10*'Ratio Analysis & Interpretation'!Q15/365 -> 16902.134 | R31: =R10*'Ratio Analysis & Interpretation'!R15/365 -> 17914.264 | S31: =S10*'Ratio Analysis & Interpretation'!S15/365 -> 18885.091 | T31: =T10*'Ratio Analysis & Interpretation'!T15/365 -> 19811.305 | U31: =U10*'Ratio Analysis & Interpretation'!U15/365 -> 20690.638 | V31: =V10*'Ratio Analysis & Interpretation'!V15/365 -> 21521.756
D32: Inventory | H32: ='Historical Info'!H47 -> 63511.28 | I32: ='Historical Info'!I47 -> 76948.56 | J32: ='Historical Info'!J47 -> 36530.42 | K32: ='Historical Info'!K47 -> 48506.78 | L32: ='Historical Info'!L47 -> 52631.9 | M32: =-M11*'Ratio Analysis & Interpretation'!M16/365 -> 65752.05 | N32: =-N11*'Ratio Analysis & Interpretation'!N16/365 -> 71621.666 | O32: =-O11*'Ratio Analysis & Interpretation'!O16/365 -> 77407.865 | P32: =-P11*'Ratio Analysis & Interpretation'!P16/365 -> 83067.424 | Q32: =-Q11*'Ratio Analysis & Interpretation'!Q16/365 -> 88563.805 | R32: =-R11*'Ratio Analysis & Interpretation'!R16/365 -> 93867.164 | S32: =-S11*'Ratio Analysis & Interpretation'!S16/365 -> 98954.108 | T32: =-T11*'Ratio Analysis & Interpretation'!T16/365 -> 103807.28 | ... V32: =-V11*'Ratio Analysis & Interpretation'!V16/365 -> 112769.7
D33: Other Current Assets | H33: ='Historical Info'!H52+'Historical Info'!H53+'Historical Info'!H54 -> 6422.28 | I33: ='Historical Info'!I52+'Historical Info'!I53+'Historical Info'!I54 -> 5675.46 | J33: ='Historical Info'!J52+'Historical Info'!J53+'Historical Info'!J54 -> 6353.26 | K33: ='Historical Info'!K52+'Historical Info'!K53+'Historical Info'!K54 -> 6207.65 | L33: ='Historical Info'!L52+'Historical Info'!L53+'Historical Info'!L54 -> 5807.37 | M33: =L33 -> 5807.37 | N33: =M33 -> 5807.37 | O33: =N33 -> 5807.37 | P33: =O33 -> 5807.37 | Q33: =P33 -> 5807.37 | R33: =Q33 -> 5807.37 | S33: =R33 -> 5807.37 | T33: =S33 -> 5807.37 | ... V33: =U33 -> 5807.37
C35: Non-current Assets
D36: Property, Plant & Equipments | H36: ='Historical Info'!H37+'Historical Info'!H38 -> 13092.66 | I36: ='Historical Info'!I37+'Historical Info'!I38 -> 23090.44 | J36: ='Historical Info'!J37+'Historical Info'!J38 -> 26142.36 | K36: ='Historical Info'!K37+'Historical Info'!K38 -> 33293.48 | L36: ='Historical Info'!L37+'Historical Info'!L38 -> 38219.29 | M36: ='Working Schedules'!M17 -> 43497.451 | N36: ='Working Schedules'!N17 -> 48381.785 | O36: ='Working Schedules'!O17 -> 51937.4 | P36: ='Working Schedules'!P17 -> 55170.79 | Q36: ='Working Schedules'!Q17 -> 58115.23 | R36: ='Working Schedules'!R17 -> 59638.277 | S36: ='Working Schedules'!S17 -> 61017.832 | T36: ='Working Schedules'!T17 -> 62271.705 | ... V36: ='Working Schedules'!V17 -> 62126.853
D37: Goodwill | H37: ='Historical Info'!H41 -> 2.8 | I37: ='Historical Info'!I41 -> 2.52 | J37: ='Historical Info'!J41 -> 9.1 | K37: ='Historical Info'!K41 -> 7.65 | L37: ='Historical Info'!L41 -> 3.52 | M37: =L37 -> 3.52 | N37: =M37 -> 3.52 | O37: =N37 -> 3.52 | P37: =O37 -> 3.52 | Q37: =P37 -> 3.52 | R37: =Q37 -> 3.52 | S37: =R37 -> 3.52 | T37: =S37 -> 3.52 | ... V37: =U37 -> 3.52
D38: Financial Assets | H38: =SUM('Historical Info'!H43,'Historical Info'!H44,'Historical Info'!H39) -> 382.91 | I38: =SUM('Historical Info'!I43,'Historical Info'!I44,'Historical Info'!I39) -> 377.59 | J38: =SUM('Historical Info'!J43,'Historical Info'!J44,'Historical Info'!J39) -> 365.27 | K38: =SUM('Historical Info'!K43,'Historical Info'!K44,'Historical Info'!K39) -> 359.9 | L38: =SUM('Historical Info'!L43,'Historical Info'!L44,'Historical Info'!L39) -> 514.5 | M38: =L38 -> 514.5 | N38: =M38 -> 514.5 | O38: =N38 -> 514.5 | P38: =O38 -> 514.5 | Q38: =P38 -> 514.5 | R38: =Q38 -> 514.5 | S38: =R38 -> 514.5 | T38: =S38 -> 514.5 | ... V38: =U38 -> 514.5
D39: Other Non-Current Assets | H39: ='Historical Info'!H45 -> 326.1 | I39: ='Historical Info'!I45 -> 612.13 | J39: ='Historical Info'!J45 -> 1670.12 | K39: ='Historical Info'!K45 -> 1877.94 | L39: ='Historical Info'!L45 -> 1949.93 | M39: =L39 -> 1949.93 | N39: =M39 -> 1949.93 | O39: =N39 -> 1949.93 | P39: =O39 -> 1949.93 | Q39: =P39 -> 1949.93 | R39: =Q39 -> 1949.93 | S39: =R39 -> 1949.93 | T39: =S39 -> 1949.93 | ... V39: =U39 -> 1949.93
D40: Total Assets | H40: =SUM(H29:H33,H36:H39) -> 89342.74 | I40: =SUM(I29:I33,I36:I39) -> 116364.81 | J40: =SUM(J29:J33,J36:J39) -> 91637.94 | K40: =SUM(K29:K33,K36:K39) -> 108525.08 | L40: =SUM(L29:L33,L36:L39) -> 113062.66 | M40: =SUM(M29:M33,M36:M39) -> 121518.19 | N40: =SUM(N29:N33,N36:N39) -> 125297.66 | O40: =SUM(O29:O33,O36:O39) -> 128808.78 | ... V40: =SUM(V29:V33,V36:V39) -> 158215.85
B42: LIABILITIES
C43: Current Liabilities
D44: Account Payables | H44: =SUM('Historical Info'!H73,'Historical Info'!H74,'Historical Info'!H75,'Historical Info'!H76,'Historical Info'!H77) -> 11749.81 | I44: =SUM('Historical Info'!I73,'Historical Info'!I74,'Historical Info'!I75,'Historical Info'!I76,'Historical Info'!I77) -> 23169.03 | J44: =SUM('Historical Info'!J73,'Historical Info'!J74,'Historical Info'!J75,'Historical Info'!J76,'Historical Info'!J77) -> 15611.66 | K44: =SUM('Historical Info'!K73,'Historical Info'!K74,'Historical Info'!K75,'Historical Info'!K76,'Historical Info'!K77) -> 18500.87 | L44: =SUM('Historical Info'!L73,'Historical Info'!L74,'Historical Info'!L75,'Historical Info'!L76,'Historical Info'!L77) -> 11830.52 | M44: =-M11*'Ratio Analysis & Interpretation'!M17/365 -> 18552.883 | N44: =-N11*'Ratio Analysis & Interpretation'!N17/365 -> 20209.079 | O44: =-O11*'Ratio Analysis & Interpretation'!O17/365 -> 21841.738 | P44: =-P11*'Ratio Analysis & Interpretation'!P17/365 -> 23438.664 | Q44: =-Q11*'Ratio Analysis & Interpretation'!Q17/365 -> 24989.546 | R44: =-R11*'Ratio Analysis & Interpretation'!R17/365 -> 26485.965 | S44: =-S11*'Ratio Analysis & Interpretation'!S17/365 -> 27921.319 | T44: =-T11*'Ratio Analysis & Interpretation'!T17/365 -> 29290.711 | ... V44: =-V11*'Ratio Analysis & Interpretation'!V17/365 -> 31819.587
D45: Other Current Liabilities | H45: =SUM('Historical Info'!H78,'Historical Info'!H79,'Historical Info'!H80,'Historical Info'!H81) -> 12820.8 | I45: =SUM('Historical Info'!I78,'Historical Info'!I79,'Historical Info'!I80,'Historical Info'!I81) -> 15760.04 | J45: =SUM('Historical Info'!J78,'Historical Info'!J79,'Historical Info'!J80,'Historical Info'!J81) -> 17791.8 | K45: =SUM('Historical Info'!K78,'Historical Info'!K79,'Historical Info'!K80,'Historical Info'!K81) -> 13728.77 | L45: =SUM('Historical Info'!L78,'Historical Info'!L79,'Historical Info'!L80,'Historical Info'!L81) -> 17681.41 | M45: =L45 -> 17681.41 | N45: =M45 -> 17681.41 | O45: =N45 -> 17681.41 | P45: =O45 -> 17681.41 | Q45: =P45 -> 17681.41 | R45: =Q45 -> 17681.41 | S45: =R45 -> 17681.41 | T45: =S45 -> 17681.41 | ... V45: =U45 -> 17681.41
C46: Non-Current Liabilities
D47: Debt | H47: ='Historical Info'!H66+'Historical Info'!H71 -> 55416.12 | I47: ='Historical Info'!I66+'Historical Info'!I71 -> 63968.33 | J47: ='Historical Info'!J66+'Historical Info'!J71 -> 34718.35 | K47: ='Historical Info'!K66+'Historical Info'!K71 -> 51383.83 | L47: ='Historical Info'!L66+'Historical Info'!L71 -> 61097.96 | M47: ='Working Schedules'!M22 -> 61097.96 | N47: ='Working Schedules'!N22 -> 61097.96 | O47: ='Working Schedules'!O22 -> 61097.96 | P47: ='Working Schedules'!P22 -> 61097.96 | Q47: ='Working Schedules'!Q22 -> 61097.96 | R47: ='Working Schedules'!R22 -> 61097.96 | S47: ='Working Schedules'!S22 -> 61097.96 | T47: ='Working Schedules'!T22 -> 61097.96 | ... V47: ='Working Schedules'!V22 -> 61097.96
D48: Other Non-Current Liabilities | H48: =SUM('Historical Info'!H68,'Historical Info'!H67) -> 1306.02 | I48: =SUM('Historical Info'!I68,'Historical Info'!I67) -> 1291.17 | J48: =SUM('Historical Info'!J68,'Historical Info'!J67) -> 1432.69 | K48: =SUM('Historical Info'!K68,'Historical Info'!K67) -> 1414.8 | L48: =SUM('Historical Info'!L68,'Historical Info'!L67) -> 852.66 | M48: =L48 -> 852.66 | N48: =M48 -> 852.66 | O48: =N48 -> 852.66 | P48: =O48 -> 852.66 | Q48: =P48 -> 852.66 | R48: =Q48 -> 852.66 | S48: =R48 -> 852.66 | T48: =S48 -> 852.66 | ... V48: =U48 -> 852.66
D49: Total Liabilities | H49: =SUM(H44:H45,H47:H48) -> 81292.75 | I49: =SUM(I44:I45,I47:I48) -> 104188.57 | J49: =SUM(J44:J45,J47:J48) -> 69554.5 | K49: =SUM(K44:K45,K47:K48) -> 85028.27 | L49: =SUM(L44:L45,L47:L48) -> 91462.55 | M49: =SUM(M44:M45,M47:M48) -> 98184.913 | N49: =SUM(N44:N45,N47:N48) -> 99841.109 | O49: =SUM(O44:O45,O47:O48) -> 101473.77 | ... V49: =SUM(V44:V45,V47:V48) -> 111451.62
C50: Shareholder's Equity
D51: Equity Capital | H51: ='Historical Info'!H58 -> 1125 | I51: ='Historical Info'!I58 -> 1125 | J51: ='Historical Info'!J58 -> 1125 | K51: ='Historical Info'!K58 -> 1125 | L51: ='Historical Info'!L58 -> 1125 | M51: =L51 -> 1125 | N51: =M51 -> 1125 | O51: =N51 -> 1125 | P51: =O51 -> 1125 | Q51: =P51 -> 1125 | R51: =Q51 -> 1125 | S51: =R51 -> 1125 | T51: =S51 -> 1125 | ... V51: =U51 -> 1125
D52: Retained Earnings | H52: =SUM('Historical Info'!H60:H63) -> 6924.99 | I52: =SUM('Historical Info'!I60:I63) -> 11051.24 | J52: =SUM('Historical Info'!J60:J63) -> 20958.44 | K52: =SUM('Historical Info'!K60:K63) -> 22371.81 | L52: =SUM('Historical Info'!L60:L63) -> 20475.11 | M52: =L52+M23+M78 -> 22208.274 | N52: =M52+N23+N78 -> 24331.548 | O52: =N52+O23+O78 -> 26210.013 | P52: =O52+P23+P78 -> 28498.195 | Q52: =P52+Q23+Q78 -> 31180.314 | R52: =Q52+R23+R78 -> 33518.672 | S52: =R52+S23+S78 -> 36294.524 | T52: =S52+T23+T78 -> 39509.04 | ... V52: =U52+V23+V78 -> 45639.228
D53: Shareholder's Equity | H53: =SUM(H51:H52) -> 8049.99 | I53: =SUM(I51:I52) -> 12176.24 | J53: =SUM(J51:J52) -> 22083.44 | K53: =SUM(K51:K52) -> 23496.81 | L53: =SUM(L51:L52) -> 21600.11 | M53: =SUM(M51:M52) -> 23333.274 | N53: =SUM(N51:N52) -> 25456.548 | O53: =SUM(O51:O52) -> 27335.013 | ... V53: =SUM(V51:V52) -> 46764.228
D54: Non-Controlling Interest | H54: =0 -> 0 | I54: =0 -> 0 | J54: =0 -> 0 | K54: =0 -> 0 | L54: =0 -> 0 | M54: =L54 -> 0 | N54: =M54 -> 0 | O54: =N54 -> 0 | P54: =O54 -> 0 | Q54: =P54 -> 0 | R54: =Q54 -> 0 | S54: =R54 -> 0 | T54: =S54 -> 0 | ... V54: =U54 -> 0
D55: Total Liabilities & Shareholder's Equity | H55: =SUM(H49+H53) -> 89342.74 | I55: =SUM(I49+I53) -> 116364.81 | J55: =SUM(J49+J53) -> 91637.94 | K55: =SUM(K49+K53) -> 108525.08 | L55: =SUM(L49+L53) -> 113062.66 | M55: =SUM(M49+M53) -> 121518.19 | N55: =SUM(N49+N53) -> 125297.66 | O55: =SUM(O49+O53) -> 128808.78 | ... V55: =SUM(V49+V53) -> 158215.85
D57: Check | H57: =IF(H55=H40,"Perfect",H40-H55) -> Perfect | I57: =IF(I55=I40,"Perfect",I40-I55) -> Perfect | J57: =IF(J55=J40,"Perfect",J40-J55) -> Perfect | K57: =IF(K55=K40,"Perfect",K40-K55) -> Perfect | L57: =IF(L55=L40,"Perfect",L40-L55) -> Perfect | M57: =IF(M55=M40,"Perfect",M40-M55) -> Perfect | N57: =IF(N55=N40,"Perfect",N40-N55) -> Perfect | O57: =IF(O55=O40,"Perfect",O40-O55) -> Perfect | ... V57: =IF(V55=V40,"Perfect",V40-V55) -> Perfect
A59: Cashflow Statement
C60: Operating Cash flow
D61: Net Earnings | F61: =F28 -> ₹ in Lakhs | H61: =SUM('Historical Info'!H88,'Historical Info'!H102) -> 1909.08 | I61: =SUM('Historical Info'!I88,'Historical Info'!I102) -> 4295.87 | J61: =SUM('Historical Info'!J88,'Historical Info'!J102) -> 11936.24 | K61: =SUM('Historical Info'!K88,'Historical Info'!K102) -> 1084.56 | L61: =SUM('Historical Info'!L88,'Historical Info'!L102) -> -2245.23 | M61: =M23 -> 1931.7767 | N61: =N23 -> 2366.5915 | O61: =O23 -> 2093.7285 | P61: =P23 -> 2550.3974 | Q61: =Q23 -> 2989.478 | R61: =R23 -> 2606.3225 | S61: =S23 -> 3093.9522 | T61: =T23 -> 3582.8851 | ... V61: =V23 -> 3693.1888
D62: Plus: Depreciation and Amortization | H62: ='Historical Info'!H90 -> 1242.62 | I62: ='Historical Info'!I90 -> 1148.05 | J62: ='Historical Info'!J90 -> 1807.98 | K62: ='Historical Info'!K90 -> 2908.21 | L62: ='Historical Info'!L90 -> 2750.2 | M62: =-M17 -> 3157.1068 | N62: =-N17 -> 3593.1096 | O62: =-O17 -> 4964.2161 | P62: =-P17 -> 5329.0402 | Q62: =-Q17 -> 5660.8024 | R62: =-R17 -> 7125.2214 | S62: =-S17 -> 7311.9547 | T62: =-T17 -> 7481.0952 | ... V62: =-V17 -> 8865.7691
D63: Plus/Less: Adjustments for Non Operating Items | H63: =SUM('Historical Info'!H91,'Historical Info'!H92,'Historical Info'!H93,'Historical Info'!H94,'Historical Info'!H95,'Historical Info'!H96) -> 4241.17 | I63: =SUM('Historical Info'!I91,'Historical Info'!I92,'Historical Info'!I93,'Historical Info'!I94,'Historical Info'!I95,'Historical Info'!I96) -> 4670.67 | J63: =SUM('Historical Info'!J91,'Historical Info'!J92,'Historical Info'!J93,'Historical Info'!J94,'Historical Info'!J95,'Historical Info'!J96) -> 4881.35 | K63: =SUM('Historical Info'!K91,'Historical Info'!K92,'Historical Info'!K93,'Historical Info'!K94,'Historical Info'!K95,'Historical Info'!K96) -> 4308.17 | L63: =SUM('Historical Info'!L91,'Historical Info'!L92,'Historical Info'!L93,'Historical Info'!L94,'Historical Info'!L95,'Historical Info'!L96) -> 4450.27 | M63: =-M19-M20 -> 4340.5364 | N63: =-N19-N20 -> 4214.385 | O63: =-O19-O20 -> 4090.0265 | P63: =-P19-P20 -> 3968.3897 | Q63: =-Q19-Q20 -> 3850.26 | R63: =-R19-R20 -> 3736.2789 | S63: =-S19-S20 -> 3626.9489 | T63: =-T19-T20 -> 3522.6432 | ... V63: =-V19-V20 -> 3330.0204
D64: Plus/Less: Adjustments for Operating Assets & Liabilities | H64: ='Working Schedules'!H11 -> -15169.45 | I64: ='Working Schedules'!I11 -> -814.43 | J64: ='Working Schedules'!J11 -> 20779.29 | K64: ='Working Schedules'!K11 -> -12032.74 | L64: ='Working Schedules'!L11 -> -2824.66 | M64: ='Working Schedules'!M11 -> -6903.4966 | N64: ='Working Schedules'!N11 -> -5333.618 | O64: ='Working Schedules'!O11 -> -5257.8187 | ... V64: ='Working Schedules'!V11 -> -3957.2169
D65: Cash from Operations | H65: =SUM(H61:H64) -> -7776.58 | I65: =SUM(I61:I64) -> 9300.16 | J65: =SUM(J61:J64) -> 39404.86 | K65: =SUM(K61:K64) -> -3731.8 | L65: =SUM(L61:L64) -> 2130.58 | M65: =SUM(M61:M64) -> 2525.9232 | N65: =SUM(N61:N64) -> 4840.4682 | O65: =SUM(O61:O64) -> 5890.1524 | ... V65: =SUM(V61:V64) -> 11931.761
C67: Investing Cash flow
D68: Investments in Property and Equipments | H68: ='Historical Info'!H107 -> -610.92 | I68: ='Historical Info'!I107 -> -13154.35 | J68: ='Historical Info'!J107 -> -5923.88 | K68: ='Historical Info'!K107 -> -10284.52 | L68: ='Historical Info'!L107 -> -7744.83 | M68: =-'Working Schedules'!M15 -> -8435.2675 | N68: =-'Working Schedules'!N15 -> -8477.4438 | O68: =-'Working Schedules'!O15 -> -8519.8311 | P68: =-'Working Schedules'!P15 -> -8562.4302 | Q68: =-'Working Schedules'!Q15 -> -8605.2424 | R68: =-'Working Schedules'!R15 -> -8648.2686 | S68: =-'Working Schedules'!S15 -> -8691.5099 | T68: =-'Working Schedules'!T15 -> -8734.9675 | ... V68: =-'Working Schedules'!V15 -> -8822.5355
D69: Sale of Property, Plant and Equipments | H69: =0 -> 0 | I69: =0 -> 0 | J69: =0 -> 0 | K69: =0 -> 0 | L69: =0 -> 0 | M69: =L69 -> 0 | N69: =M69 -> 0 | O69: =N69 -> 0 | P69: =O69 -> 0 | Q69: =P69 -> 0 | R69: =Q69 -> 0 | S69: =R69 -> 0 | T69: =S69 -> 0 | ... V69: =U69 -> 0
D70: Net Proceeds From the Sale of Investments | H70: ='Historical Info'!H108 -> -1.04 | I70: ='Historical Info'!I108 -> 0 | J70: ='Historical Info'!J108 -> -1.41 | K70: ='Historical Info'!K108 -> 0 | L70: ='Historical Info'!L108 -> 0 | M70: =L38-M38 -> 0 | N70: =M38-N38 -> 0 | O70: =N38-O38 -> 0 | P70: =O38-P38 -> 0 | Q70: =P38-Q38 -> 0 | R70: =Q38-R38 -> 0 | S70: =R38-S38 -> 0 | T70: =S38-T38 -> 0 | ... V70: =U38-V38 -> 0
D71: Advance Given for Investment | H71: ='Historical Info'!H109 -> -5.75 | I71: ='Historical Info'!I109 -> 0 | J71: ='Historical Info'!J109 -> 0 | K71: ='Historical Info'!K109 -> 0 | L71: ='Historical Info'!L109 -> 72 | M71: 0 | N71: 0 | O71: 0 | P71: 0 | Q71: 0 | R71: 0 | S71: 0 | T71: 0 | U71: 0 | V71: 0
D72: Interest & Dividend received | H72: ='Historical Info'!H110 -> 67.12 | I72: ='Historical Info'!I110 -> 21.26 | J72: ='Historical Info'!J110 -> 1083.44 | K72: ='Historical Info'!K110 -> 458.52 | L72: ='Historical Info'!L110 -> 414.43 | M72: =M20 -> 1413.1606 | N72: =N20 -> 1539.3119 | O72: =O20 -> 1663.6705 | P72: =P20 -> 1785.3072 | Q72: =Q20 -> 1903.4369 | R72: =R20 -> 2017.4181 | S72: =S20 -> 2126.7481 | T72: =T20 -> 2231.0537 | ... V72: =V20 -> 2423.6765
D73: Cash from Investing | H73: =SUM(H68:H72) -> -550.59 | I73: =SUM(I68:I72) -> -13133.09 | J73: =SUM(J68:J72) -> -4841.85 | K73: =SUM(K68:K72) -> -9826 | L73: =SUM(L68:L72) -> -7258.4 | M73: =SUM(M68:M72) -> -7022.1069 | N73: =SUM(N68:N72) -> -6938.1319 | O73: =SUM(O68:O72) -> -6856.1606 | ... V73: =SUM(V68:V72) -> -6398.859
C75: Financial Cash Flow
D76: Issuance (Repayment) of Debt | H76: ='Historical Info'!H114+'Historical Info'!H115 -> 12173.36 | I76: ='Historical Info'!I114+'Historical Info'!I115 -> 8552.22 | J76: ='Historical Info'!J114+'Historical Info'!J115 -> -29508.12 | K76: ='Historical Info'!K114+'Historical Info'!K115 -> 18065.53 | L76: ='Historical Info'!L114+'Historical Info'!L115 -> 10304.19 | M76: ='Working Schedules'!M21 -> 0 | N76: ='Working Schedules'!N21 -> 0 | O76: ='Working Schedules'!O21 -> 0 | P76: ='Working Schedules'!P21 -> 0 | Q76: ='Working Schedules'!Q21 -> 0 | R76: ='Working Schedules'!R21 -> 0 | S76: ='Working Schedules'!S21 -> 0 | T76: ='Working Schedules'!T21 -> 0 | ... V76: ='Working Schedules'!V21 -> 0
D77: Issuance (Redemption) of Preference share- NCI | H77: =0 -> 0 | I77: =0 -> 0 | J77: =0 -> 0 | K77: =0 -> 0 | L77: =0 -> 0 | M77: 0 | N77: 0 | O77: 0 | P77: 0 | Q77: 0 | R77: 0 | S77: 0 | T77: 0 | U77: 0 | V77: 0
D78: Dividends paid | H78: ='Historical Info'!H116 -> -112.5 | I78: ='Historical Info'!I116 -> -225 | J78: ='Historical Info'!J116 -> -281.25 | K78: ='Historical Info'!K116 -> -562.5 | L78: ='Historical Info'!L116 -> -281.25 | M78: =IF(M23>0,-M23*'Ratio Analysis & Interpretation'!M14,0) -> -198.61271 | N78: =IF(N23>0,-N23*'Ratio Analysis & Interpretation'!N14,0) -> -243.31754 | O78: =IF(O23>0,-O23*'Ratio Analysis & Interpretation'!O14,0) -> -215.26354 | P78: =IF(P23>0,-P23*'Ratio Analysis & Interpretation'!P14,0) -> -262.21526 | Q78: =IF(Q23>0,-Q23*'Ratio Analysis & Interpretation'!Q14,0) -> -307.35867 | R78: =IF(R23>0,-R23*'Ratio Analysis & Interpretation'!R14,0) -> -267.96512 | S78: =IF(S23>0,-S23*'Ratio Analysis & Interpretation'!S14,0) -> -318.10003 | T78: =IF(T23>0,-T23*'Ratio Analysis & Interpretation'!T14,0) -> -368.36893 | ... V78: =IF(V23>0,-V23*'Ratio Analysis & Interpretation'!V14,0) -> -379.70964
D79: Interests paid | H79: ='Historical Info'!H113 -> -4189.16 | I79: ='Historical Info'!I113 -> -4412.13 | J79: ='Historical Info'!J113 -> -4821.85 | K79: ='Historical Info'!K113 -> -4427.44 | L79: ='Historical Info'!L113 -> -4820.18 | M79: ='Working Schedules'!M23 -> -5753.697 | N79: ='Working Schedules'!N23 -> -5753.697 | O79: ='Working Schedules'!O23 -> -5753.697 | P79: ='Working Schedules'!P23 -> -5753.697 | Q79: ='Working Schedules'!Q23 -> -5753.697 | R79: ='Working Schedules'!R23 -> -5753.697 | S79: ='Working Schedules'!S23 -> -5753.697 | T79: ='Working Schedules'!T23 -> -5753.697 | ... V79: ='Working Schedules'!V23 -> -5753.697
D80: Cash from Financing | H80: =SUM(H76:H79) -> 7871.7 | I80: =SUM(I76:I79) -> 3915.09 | J80: =SUM(J76:J79) -> -34611.22 | K80: =SUM(K76:K79) -> 13075.59 | L80: =SUM(L76:L79) -> 5202.76 | M80: =SUM(M76:M79) -> -5952.3097 | N80: =SUM(N76:N79) -> -5997.0145 | O80: =SUM(O76:O79) -> -5968.9605 | ... V80: =SUM(V76:V79) -> -6133.4066
D82: Net Increase (Decrease) in Cash | H82: =SUM(H65,H73,H80) -> -455.47 | I82: =SUM(I65,I73,I80) -> 82.16 | J82: =SUM(J65,J73,J80) -> -48.21 | K82: =SUM(K65,K73,K80) -> -482.21 | L82: =SUM(L65,L73,L80) -> 74.94 | M82: =SUM(M65,M73,M80) -> -10448.493 | N82: =SUM(N65,N73,N80) -> -8094.6782 | O82: =SUM(O65,O73,O80) -> -6934.9687 | ... V82: =SUM(V65,V73,V80) -> -600.50418
D83: Opening Cash Balance | H83: ='Historical Info'!H119 -> 997.56 | I83: ='Historical Info'!I119 -> 542.1 | J83: ='Historical Info'!J119 -> 624.26 | K83: ='Historical Info'!K119 -> 576.05 | L83: ='Historical Info'!L119 -> 93.84 | M83: =L84 -> 168.78 | N83: =M84 -> -10279.713 | O83: =N84 -> -18374.392 | P83: =O84 -> -25309.36 | Q83: =P84 -> -31397.312 | R83: =Q84 -> -36654.099 | S83: =R84 -> -40657.858 | T83: =S84 -> -43883.979 | ... V83: =U84 -> -47601.784
D84: Closing Cash Balance | H84: =SUM(H82:H83) -> 542.09 | I84: =SUM(I82:I83) -> 624.26 | J84: =SUM(J82:J83) -> 576.05 | K84: =SUM(K82:K83) -> 93.84 | L84: =SUM(L82:L83) -> 168.78 | M84: =SUM(M82:M83) -> -10279.713 | N84: =SUM(N82:N83) -> -18374.392 | O84: =SUM(O82:O83) -> -25309.36 | ... V84: =SUM(V82:V83) -> -48202.289
D86: Check=> Cash in BS is = Closing Cash in CF | H86: =H84-H29 -> 0 | I86: =I84-I29 -> -1.0231815e-12 | J86: =J84-J29 -> 9.094947e-13 | K86: =K84-K29 -> -9.9475983e-13 | L86: =L84-L29 -> 5.1159077e-13 | M86: =M84-M29 -> 0 | N86: =N84-N29 -> 0 | O86: =O84-O29 -> 0 | ... V86: =V84-V29 -> 0

Sheet DCF
A1: ='Historical Info'!A1 -> Ugar Sugar Works Ltd.
A2: Revenue Growth Scenarios
A4: DCF Analysis
D6: Assumptions
D7: Transaction date | E7: 46064
D8: Fiscal Year end | E8: =EOMONTH(E7,1) -> 46112
D9: Tax rate | E9: ='Comps (Data)'!K11 -> 0.27409762
D10: EV/EBITDA multiple | E10: ='Comps Valuation'!S20 -> 11.463405
D11: Perpetual Growth Rate | E11: 0.04
D12: Discount Rate (WACC) | E12: =WACC!H43 -> 0.076468305
D13: Shares Outstanding | E13: ='Comps (Data)'!D11 -> 1125.3063
D14: Current Market Price | E14: ='Comps Valuation'!H20 -> 39.33
A17: Unlevered Free Cash Flow
H18: Historical FCFF | M18: DCF- FCFF
D19: Discounted Cash Flow | H19: ='Financial Statements'!H2 -> 2021 | I19: ='Financial Statements'!I2 -> 2022 | J19: ='Financial Statements'!J2 -> 2023 | K19: ='Financial Statements'!K2 -> 2024 | L19: ='Financial Statements'!L2 -> 2025 | M19: Entry Date | N19: ='Financial Statements'!M2 -> 2026 | O19: ='Financial Statements'!N2 -> 2027 | P19: ='Financial Statements'!O2 -> 2028 | Q19: ='Financial Statements'!P2 -> 2029 | R19: ='Financial Statements'!Q2 -> 2030 | S19: ='Financial Statements'!R2 -> 2031 | T19: ='Financial Statements'!S2 -> 2032 | U19: ='Financial Statements'!T2 -> 2033 | ... W19: ='Financial Statements'!V2 -> 2035 | X19: Exit
D20: Date | M20: =E7 -> 46064 | N20: =DATE(YEAR($M$20)+N21,MONTH($E$8),DAY($E$8)) -> 46112 | O20: =DATE(YEAR($M$20)+O21,MONTH($E$8),DAY($E$8)) -> 46477 | P20: =DATE(YEAR($M$20)+P21,MONTH($E$8),DAY($E$8)) -> 46843 | Q20: =DATE(YEAR($M$20)+Q21,MONTH($E$8),DAY($E$8)) -> 47208 | R20: =DATE(YEAR($M$20)+R21,MONTH($E$8),DAY($E$8)) -> 47573 | S20: =DATE(YEAR($M$20)+S21,MONTH($E$8),DAY($E$8)) -> 47938 | T20: =DATE(YEAR($M$20)+T21,MONTH($E$8),DAY($E$8)) -> 48304 | U20: =DATE(YEAR($M$20)+U21,MONTH($E$8),DAY($E$8)) -> 48669 | ... W20: =DATE(YEAR($M$20)+W21,MONTH($E$8),DAY($E$8)) -> 49399 | X20: =W20 -> 49399
D21: Time period | N21: 0 | O21: =N21+1 -> 1 | P21: =O21+1 -> 2 | Q21: =P21+1 -> 3 | R21: =Q21+1 -> 4 | S21: =R21+1 -> 5 | T21: =S21+1 -> 6 | U21: =T21+1 -> 7 | V21: =U21+1 -> 8 | W21: =V21+1 -> 9
D22: Yearfrac | N22: =YEARFRAC(M20,N20) -> 0.13888889 | O22: =YEARFRAC(N20,O20) -> 1 | P22: =YEARFRAC(O20,P20) -> 1 | Q22: =YEARFRAC(P20,Q20) -> 1 | R22: =YEARFRAC(Q20,R20) -> 1 | S22: =YEARFRAC(R20,S20) -> 1 | T22: =YEARFRAC(S20,T20) -> 1 | U22: =YEARFRAC(T20,U20) -> 1 | ... W22: =YEARFRAC(V20,W20) -> 1 | X22: =W22 -> 1
D24: EBIT | I24: ='Financial Statements'!I18 -> 8766.21 | J24: ='Financial Statements'!J18 -> 19056.45 | K24: ='Financial Statements'!K18 -> 4112.46 | L24: ='Financial Statements'!L18 -> 1292.99 | N24: ='Financial Statements'!M18 -> 6987.1597 | O24: ='Financial Statements'!N18 -> 7456.7248 | P24: ='Financial Statements'!O18 -> 6978.3167 | Q24: ='Financial Statements'!P18 -> 7486.6529 | R24: ='Financial Statements'!Q18 -> 8002.8758 | S24: ='Financial Statements'!R18 -> 7356.6621 | T24: ='Financial Statements'!S18 -> 7954.7457 | U24: ='Financial Statements'!T18 -> 8534.3556 | ... W24: ='Financial Statements'!V18 -> 8532.41
D25: Less: Cash Tax | I25: ='Financial Statements'!I22 -> -304 | J25: ='Financial Statements'!J22 -> -4534.44 | K25: ='Financial Statements'!K22 -> -865.89 | L25: ='Financial Statements'!L22 -> 586.16 | N25: ='Financial Statements'!M22 -> -714.84667 | O25: ='Financial Statements'!N22 -> -875.74827 | P25: ='Financial Statements'!O22 -> -794.56177 | Q25: ='Financial Statements'!P22 -> -967.86583 | R25: ='Financial Statements'!Q22 -> -1163.1378 | S25: ='Financial Statements'!R22 -> -1014.0607 | T25: ='Financial Statements'!S22 -> -1233.8446 | U25: ='Financial Statements'!T22 -> -1428.8273 | ... W25: ='Financial Statements'!V22 -> -1509.2009
D26: NOPAT | I26: =SUM(I24:I25) -> 8462.21 | J26: =SUM(J24:J25) -> 14522.01 | K26: =SUM(K24:K25) -> 3246.57 | L26: =SUM(L24:L25) -> 1879.15 | N26: =SUM(N24:N25) -> 6272.313 | O26: =SUM(O24:O25) -> 6580.9766 | P26: =SUM(P24:P25) -> 6183.755 | Q26: =SUM(Q24:Q25) -> 6518.7871 | R26: =SUM(R24:R25) -> 6839.738 | S26: =SUM(S24:S25) -> 6342.6014 | T26: =SUM(T24:T25) -> 6720.9011 | U26: =SUM(U24:U25) -> 7105.5283 | ... W26: =SUM(W24:W25) -> 7023.2092
D27: Plus: D&A | I27: =-'Financial Statements'!I17 -> 1148.05 | J27: =-'Financial Statements'!J17 -> 1807.97 | K27: =-'Financial Statements'!K17 -> 2908.21 | L27: =-'Financial Statements'!L17 -> 2750.21 | N27: =-'Financial Statements'!M17 -> 3157.1068 | O27: =-'Financial Statements'!N17 -> 3593.1096 | P27: =-'Financial Statements'!O17 -> 4964.2161 | Q27: =-'Financial Statements'!P17 -> 5329.0402 | R27: =-'Financial Statements'!Q17 -> 5660.8024 | S27: =-'Financial Statements'!R17 -> 7125.2214 | T27: =-'Financial Statements'!S17 -> 7311.9547 | U27: =-'Financial Statements'!T17 -> 7481.0952 | ... W27: =-'Financial Statements'!V17 -> 8865.7691
D28: Less: Capex | I28: =-'Working Schedules'!I15 -> -11145.83 | J28: =-'Working Schedules'!J15 -> -4859.9 | K28: =-'Working Schedules'!K15 -> -10059.33 | L28: =-'Working Schedules'!L15 -> -7676.01 | N28: =-'Working Schedules'!M15 -> -8435.2675 | O28: =-'Working Schedules'!N15 -> -8477.4438 | P28: =-'Working Schedules'!O15 -> -8519.8311 | Q28: =-'Working Schedules'!P15 -> -8562.4302 | R28: =-'Working Schedules'!Q15 -> -8605.2424 | S28: =-'Working Schedules'!R15 -> -8648.2686 | T28: =-'Working Schedules'!S15 -> -8691.5099 | U28: =-'Working Schedules'!T15 -> -8734.9675 | ... W28: =-'Working Schedules'!V15 -> -8822.5355
D29: Less: Changes in Net WC | I29: ='Working Schedules'!I11 -> -814.43 | J29: ='Working Schedules'!J11 -> 20779.29 | K29: ='Working Schedules'!K11 -> -12032.74 | L29: ='Working Schedules'!L11 -> -2824.66 | N29: ='Working Schedules'!M11 -> -6903.4966 | O29: ='Working Schedules'!N11 -> -5333.618 | P29: ='Working Schedules'!O11 -> -5257.8187 | Q29: ='Working Schedules'!P11 -> -5142.7434 | R29: ='Working Schedules'!Q11 -> -4994.4663 | S29: ='Working Schedules'!R11 -> -4819.0695 | T29: ='Working Schedules'!S11 -> -4622.4178 | U29: ='Working Schedules'!T11 -> -4409.9931 | ... W29: ='Working Schedules'!V11 -> -3957.2169
D30: Unlevered Free Cash Flow | I30: =SUM(I26:I29) -> -2350 | J30: =SUM(J26:J29) -> 32249.37 | K30: =SUM(K26:K29) -> -15937.29 | L30: =SUM(L26:L29) -> -5871.31 | M30: 0 | N30: =SUM(N26:N29) -> -5909.3443 | O30: =SUM(O26:O29) -> -3636.9756 | P30: =SUM(P26:P29) -> -2629.6787 | Q30: =SUM(Q26:Q29) -> -1857.3463 | R30: =SUM(R26:R29) -> -1099.1683 | S30: =SUM(S26:S29) -> 0.4846723 | T30: =SUM(T26:T29) -> 718.92808 | U30: =SUM(U26:U29) -> 1441.6629 | ... W30: =SUM(W26:W29) -> 3109.2259 | X30: =S39 -> 144055.51
D32: Transaction Cash flow | M32: =M30 -> 0 | N32: =N30*N22 -> -820.74226 | O32: =O30*O22 -> -3636.9756 | P32: =P30*P22 -> -2629.6787 | Q32: =Q30*Q22 -> -1857.3463 | R32: =R30*R22 -> -1099.1683 | S32: =S30*S22 -> 0.4846723 | T32: =T30*T22 -> 718.92808 | U32: =U30*U22 -> 1441.6629 | ... X32: =X30*X22 -> 144055.51
D35: Intrinsic Value (Using Implied Value) | I35: Market Value (Using Facts) | M35: Rate of Return
D36: Enterprise Value | E36: =SUM(M32:X32) -> 141759.84 | I36: Market Cap | K36: =E13*E14 -> 44258.298 | M36: Current Price | O36: =K42 -> 39.33 | Q36: Terminal Value
D37: Plus: Cash & Cash Equivalents (Including Fin Assets) | E37: =SUM('Financial Statements'!L29:L30,'Financial Statements'!L38) -> 2407.78 | I37: Less: Cash | K37: =-E37 -> -2407.78 | M37: Target Price | O37: =E42 -> 73.819597 | Q37: EV/EBITDA | S37: =(W24+W27)*E10 -> 199442.38
D38: Less: Debt | E38: =-'Working Schedules'!L22 -> -61097.96 | I38: Plus: Debt | K38: =-E38 -> 61097.96 | M38: Target Potential | O38: =O37/O36-1 -> 0.87692847 | Q38: Perpetual Growth | S38: =W30*(1+E11)/(E12-E11) -> 88668.637
D39: Less: Non- Controlling Interest | E39: ='Financial Statements'!L54 -> 0 | I39: Plus: NCI | K39: =E39 -> 0 | Q39: Average | S39: =AVERAGE(S37:S38) -> 144055.51
D40: Equity Value | E40: =SUM(E36:E39) -> 83069.66 | I40: Enterprise Value | K40: =SUM(K36:K39) -> 102948.48
D42: Equity Value per share | E42: =E40/E13 -> 73.819597 | I42: Equity Value per share | K42: =K36/E13 -> 39.33
D43: (Target Price) | I43: (Market Price)
A47: Sensitivity Analysis
H49: Sensitivities - Intrinsic values (Rs. /Share)
J51: Exit Multiple
I52: =E42 -> 73.819597 | J52: 5 | K52: 10 | L52: 11.463405 | M52: 15 | N52: 20
H53: Discount Rate | I53: 0.05 | J53: 128.13342 | K53: 166.78551 | L53: 178.09825 | M53: 205.43761 | N53: 244.0897
I54: 0.06 | J54: 56.295314 | K54: 94.947409 | L54: 106.26014 | M54: 133.5995 | N54: 172.2516
I55: 0.069010736 | J55: 33.982395 | K55: 72.63449 | L55: 83.947225 | M55: 111.28659 | N55: 149.93868
I56: 0.076505354 | J56: 23.814781 | K56: 62.466876 | L56: 73.779612 | M56: 101.11897 | N56: 139.77107
I57: 0.09 | J57: 13.192452 | K57: 51.844547 | L57: 63.157283 | M57: 90.496642 | N57: 129.14874
J61: Perpetual Growth
I62: =E42 -> 73.819597 | J62: 0.02 | K62: 0.03 | L62: 0.04 | M62: 0.05 | N62: 0.06
H63: Discount Rate | I63: 0.05 | J63: 81.393109 | K63: 105.56939 | L63: 178.09825 | M63: #DIV/0! | N63: -112.01717
I64: 0.06 | J64: 69.650342 | K64: 81.853609 | L64: 106.26014 | M64: 179.47975 | N64: #DIV/0!
I65: 0.069010736 | J65: 63.173538 | K65: 70.897821 | L65: 83.947225 | M65: 110.72509 | N65: 196.9384
I66: 0.076505354 | J66: 59.360068 | K66: 65.01953 | L66: 73.779612 | M66: 89.149741 | N66: 123.14429
I67: 0.09 | J67: 54.552499 | K67: 58.137825 | L67: 63.157283 | M67: 70.686468 | N67: 83.235111
D70: Back to Cover

Sheet Comps Valuation
A1: ='Historical Info'!A1 -> Ugar Sugar Works Ltd.
A2: Comps Valuation- Values are in INR Lakhs
J5: Market Data | O5: Financial Data | S5: Valuation Metrices
H6: Price | I6: Shares | J6: Market Cap | K6: Debt | L6: Cash & Cash Equivalents | M6: Enterprise Value | N6: Sales | O6: EBITDA | P6: Earnings | Q6: Effective Tax Rate | R6: EV/Sales | S6: EV/ EBITDA | T6: P/E
D7: Company Name | F7: Ticker | H7: ₹/Share | I7: In Lakhs | J7: ₹ in Lakhs | M7: ₹ in Lakhs | N7: ₹ in Lakhs | O7: ₹ in Lakhs | P7: ₹ in Lakhs | R7: x | S7: x | T7: x
D8: ='Comps (Data)'!A2 -> Mawana Sugars Limited | F8: ='Comps (Data)'!B2 -> 523371 | H8: ='Comps (Data)'!C2 -> 79.5 | I8: ='Comps (Data)'!D2 -> 390.99666 | J8: ='Comps (Data)'!E2 -> 31097.907 | K8: ='Comps (Data)'!F2 -> 19559.408 | L8: ='Comps (Data)'!G2 -> 1521.7 | M8: =J8+K8-L8 -> 49135.615 | N8: ='Comps (Data)'!H2 -> 152953.44 | O8: ='Comps (Data)'!I2 -> 12085.844 | P8: ='Comps (Data)'!J2 -> 10172.867 | Q8: ='Comps (Data)'!K2 -> 0.164934 | R8: =M8/N8 -> 0.32124558 | S8: =M8/O8 -> 4.0655511 | T8: =J8/P8 -> 3.0569463
D9: ='Comps (Data)'!A3 -> DCM Shriram Industries Limited | F9: ='Comps (Data)'!B3 -> 523369 | H9: ='Comps (Data)'!C3 -> 37.59 | I9: ='Comps (Data)'!D3 -> 869.54098 | J9: ='Comps (Data)'!E3 -> 32700.362 | K9: ='Comps (Data)'!F3 -> 57177.206 | L9: ='Comps (Data)'!G3 -> 11028.9 | M9: =J9+K9-L9 -> 78848.668 | N9: ='Comps (Data)'!H3 -> 213747.05 | O9: ='Comps (Data)'!I3 -> 18989.116 | P9: ='Comps (Data)'!J3 -> 9313.5687 | Q9: ='Comps (Data)'!K3 -> 0.354496 | R9: =M9/N9 -> 0.36888775 | S9: =M9/O9 -> 4.1523086 | T9: =J9/P9 -> 3.5110454
D10: ='Comps (Data)'!A4 -> Magadh Sugar & Energy Limited | F10: ='Comps (Data)'!B4 -> MAGADSUGAR | H10: ='Comps (Data)'!C4 -> 417.8 | I10: ='Comps (Data)'!D4 -> 140.44682 | J10: ='Comps (Data)'!E4 -> 58874.83 | K10: ='Comps (Data)'!F4 -> 75737.668 | L10: ='Comps (Data)'!G4 -> 133.5 | M10: =J10+K10-L10 -> 134479 | N10: ='Comps (Data)'!H4 -> 138761.06 | O10: ='Comps (Data)'!I4 -> 20908.76 | P10: ='Comps (Data)'!J4 -> 10519.333 | Q10: ='Comps (Data)'!K4 -> 0.256562 | R10: =M10/N10 -> 0.96914079 | S10: =M10/O10 -> 6.431706 | T10: =J10/P10 -> 5.5968216
D11: ='Comps (Data)'!A5 -> Dwarikesh Sugar Industries Limited | F11: ='Comps (Data)'!B5 -> 532610 | H11: ='Comps (Data)'!C5 -> 33.33 | I11: ='Comps (Data)'!D5 -> 1846.9899 | J11: ='Comps (Data)'!E5 -> 61760.98 | K11: ='Comps (Data)'!F5 -> 54311.716 | L11: ='Comps (Data)'!G5 -> 29261.02 | M11: =J11+K11-L11 -> 86811.675 | N11: ='Comps (Data)'!H5 -> 152377.14 | O11: ='Comps (Data)'!I5 -> 11954.825 | P11: ='Comps (Data)'!J5 -> 2535.2519 | Q11: ='Comps (Data)'!K5 -> 0.564909 | R11: =M11/N11 -> 0.56971588 | S11: =M11/O11 -> 7.2616436 | T11: =J11/P11 -> 24.360885
D12: ='Comps (Data)'!A6 -> Avadh Sugar & Energy Limited | F12: ='Comps (Data)'!B6 -> AVADHSUGAR | H12: ='Comps (Data)'!C6 -> 322.35 | I12: ='Comps (Data)'!D6 -> 200.22026 | J12: ='Comps (Data)'!E6 -> 64529.377 | K12: ='Comps (Data)'!F6 -> 146798.27 | L12: ='Comps (Data)'!G6 -> 372.8 | M12: =J12+K12-L12 -> 210954.84 | N12: ='Comps (Data)'!H6 -> 283126.79 | O12: ='Comps (Data)'!I6 -> 26403.179 | P12: ='Comps (Data)'!J6 -> 7584.426 | Q12: ='Comps (Data)'!K6 -> 0.35483 | R12: =M12/N12 -> 0.74508967 | S12: =M12/O12 -> 7.9897517 | T12: =J12/P12 -> 8.5081425
D13: ='Comps (Data)'!A7 -> Davangere Sugar Company Limited | F13: ='Comps (Data)'!B7 -> DAVANGERE | H13: ='Comps (Data)'!C7 -> 4.59 | I13: ='Comps (Data)'!D7 -> 7290.8429 | J13: ='Comps (Data)'!E7 -> 46392.038 | K13: ='Comps (Data)'!F7 -> 38172.128 | L13: ='Comps (Data)'!G7 -> 1220.1 | M13: =J13+K13-L13 -> 83344.065 | N13: ='Comps (Data)'!H7 -> 20717.142 | O13: ='Comps (Data)'!I7 -> 5768.9815 | P13: ='Comps (Data)'!J7 -> 1210.0573 | Q13: ='Comps (Data)'!K7 -> 0.145261 | R13: =M13/N13 -> 4.0229519 | S13: =M13/O13 -> 14.446929 | T13: =J13/P13 -> 38.33871
D14: ='Comps (Data)'!A8 -> Dhampur Sugar Mills Limited | F14: ='Comps (Data)'!B8 -> 500119 | H14: ='Comps (Data)'!C8 -> 113.2 | I14: ='Comps (Data)'!D8 -> 652.05772 | J14: ='Comps (Data)'!E8 -> 72794.968 | K14: ='Comps (Data)'!F8 -> 100215.12 | L14: ='Comps (Data)'!G8 -> 25153.076 | M14: =J14+K14-L14 -> 147857.01 | N14: ='Comps (Data)'!H8 -> 211870.06 | O14: ='Comps (Data)'!I8 -> 17567.145 | P14: ='Comps (Data)'!J8 -> 5514.3263 | Q14: ='Comps (Data)'!K8 -> 0.302683 | R14: =M14/N14 -> 0.69786648 | S14: =M14/O14 -> 8.4166786 | T14: =J14/P14 -> 13.201063
D15: ='Comps (Data)'!A9 -> Uttam Sugar Mills Limited | F15: ='Comps (Data)'!B9 -> 532729 | H15: ='Comps (Data)'!C9 -> 208.7 | I15: ='Comps (Data)'!D9 -> 381.55192 | J15: ='Comps (Data)'!E9 -> 79594.256 | K15: ='Comps (Data)'!F9 -> 28639.377 | L15: ='Comps (Data)'!G9 -> 2093.5 | M15: =J15+K15-L15 -> 106140.13 | N15: ='Comps (Data)'!H9 -> 227501.8 | O15: ='Comps (Data)'!I9 -> 25616.294 | P15: ='Comps (Data)'!J9 -> 11632.761 | Q15: ='Comps (Data)'!K9 -> 0.265864 | R15: =M15/N15 -> 0.46654635 | S15: =M15/O15 -> 4.1434618 | T15: =J15/P15 -> 6.8422498
D17: Average | R17: =AVERAGE(R8:R15) -> 1.0201805 | S17: =AVERAGE(S8:S15) -> 7.1135038 | T17: =AVERAGE(T8:T15) -> 12.926983
D18: Median | R18: =MEDIAN(R8:R15) -> 0.63379118 | S18: =MEDIAN(S8:S15) -> 6.8466748 | T18: =MEDIAN(T8:T15) -> 7.6751961
D20: ='Comps (Data)'!A11 -> The Ugar Sugar Works Limited | F20: ='Comps (Data)'!B11 -> 530363 | H20: ='Comps (Data)'!C11 -> 39.33 | I20: ='Comps (Data)'!D11 -> 1125.3063 | J20: ='Comps (Data)'!E11 -> 44258.298 | K20: ='Comps (Data)'!F11 -> 45440.079 | L20: ='Comps (Data)'!G11 -> 1916.7361 | M20: =J20+K20-L20 -> 87781.642 | N20: ='Comps (Data)'!H11 -> 159888.72 | O20: ='Comps (Data)'!I11 -> 7657.5538 | P20: ='Comps (Data)'!J11 -> 1002.5592 | Q20: ='Comps (Data)'!K11 -> 0.27409762 | R20: =M20/N20 -> 0.5490171 | S20: =M20/O20 -> 11.463405 | T20: =J20/P20 -> 44.145321
D22: Metrix | F22: Comps | H22: EV | I22: Net Debt | J22: Equity Value | K22: Shares Outstanding | L22: Share Price
D23: EV/Sales | F23: =R18 -> 0.63379118 | H23: =F23*N20 -> 101336.06 | I23: =K20-L20 -> 43523.343 | J23: =H23-I23 -> 57812.717 | K23: =I20 -> 1125.3063 | L23: =J23/K23 -> 51.375092
D24: EV/ EBITDA | F24: =S18 -> 6.8466748 | H24: =F24*O20 -> 52428.78 | I24: =I23 -> 43523.343 | J24: =H24-I24 -> 8905.4371 | K24: =K23 -> 1125.3063 | L24: =J24/K24 -> 7.9137891
D25: P/E | F25: =T18 -> 7.6751961 | H25: =J25+I25 -> 51218.182 | I25: =I24 -> 43523.343 | J25: =F25*P20 -> 7694.8386 | K25: =K24 -> 1125.3063 | L25: =J25/K25 -> 6.8379946
D28: Back to Cover

Sheet Ratio Analysis & Interpretation
A1: Ugar Sugar Works Ltd.
A2: Ratio analysis & Interpretations
A4: Ratio Analysis & Interpretation | H4: ='Financial Statements'!H2 -> 2021 | I4: ='Financial Statements'!I2 -> 2022 | J4: ='Financial Statements'!J2 -> 2023 | K4: ='Financial Statements'!K2 -> 2024 | L4: ='Financial Statements'!L2 -> 2025 | M4: ='Financial Statements'!M2 -> 2026 | N4: ='Financial Statements'!N2 -> 2027 | O4: ='Financial Statements'!O2 -> 2028 | ... V4: ='Financial Statements'!V2 -> 2035 | Y4: INTERPRETATION
D6: Revenue Growth | F6: % | I6: ='Financial Statements'!I10/'Financial Statements'!H10-1 -> 0.16424864 | J6: ='Financial Statements'!J10/'Financial Statements'!I10-1 -> 0.49060072 | K6: ='Financial Statements'!K10/'Financial Statements'!J10-1 -> -0.34168135 | L6: ='Financial Statements'!L10/'Financial Statements'!K10-1 -> 0.10192011 | M6: {=CHOOSE('Financial Statements'!$G$6,'Rev Growth Scenarios'!H5:Q5,'Rev Growth Scenarios'!H6:Q6,'Rev Growth Scenarios'!H7:Q7)} -> 0.098639712 | N6: 0.089268939 | O6: 0.08078839 | P6: 0.073113493 | Q6: 0.066167711 | R6: 0.059881778 | S6: 0.054193009 | T6: 0.049044674 | U6: 0.04438543 | V6: 0.040168814
D7: COGS (% of Revenue) | F7: % | H7: =-'Financial Statements'!H11/'Financial Statements'!H10 -> 0.71024061 | I7: =-'Financial Statements'!I11/'Financial Statements'!I10 -> 0.71164868 | J7: =-'Financial Statements'!J11/'Financial Statements'!J10 -> 0.74001261 | K7: =-'Financial Statements'!K11/'Financial Statements'!K10 -> 0.74018682 | L7: =-'Financial Statements'!L11/'Financial Statements'!L10 -> 0.82932426 | M7: =AVERAGE(H7:L7) -> 0.7462826 | N7: =M7 -> 0.7462826 | O7: =N7 -> 0.7462826 | P7: =O7 -> 0.7462826 | Q7: =P7 -> 0.7462826 | R7: =Q7 -> 0.7462826 | S7: =R7 -> 0.7462826 | T7: =S7 -> 0.7462826 | U7: =T7 -> 0.7462826 | V7: =U7 -> 0.7462826
D8: Salaries & benefits (% of Revenue) | F8: % | H8: =-'Financial Statements'!H14/'Financial Statements'!H10 -> 0.062162601 | I8: =-'Financial Statements'!I14/'Financial Statements'!I10 -> 0.060263954 | J8: =-'Financial Statements'!J14/'Financial Statements'!J10 -> 0.055634321 | K8: =-'Financial Statements'!K14/'Financial Statements'!K10 -> 0.074006962 | L8: =-'Financial Statements'!L14/'Financial Statements'!L10 -> 0.062856616 | M8: =AVERAGE(H8:L8) -> 0.062984891 | N8: =M8 -> 0.062984891 | O8: =N8 -> 0.062984891 | P8: =O8 -> 0.062984891 | Q8: =P8 -> 0.062984891 | R8: =Q8 -> 0.062984891 | S8: =R8 -> 0.062984891 | T8: =S8 -> 0.062984891 | U8: =T8 -> 0.062984891 | V8: =U8 -> 0.062984891
D9: Other SG&A expenses (% of Revenue) | F9: % | H9: =-'Financial Statements'!H15/'Financial Statements'!H10 -> 0.16697279 | I9: =-'Financial Statements'!I15/'Financial Statements'!I10 -> 0.15191693 | J9: =-'Financial Statements'!J15/'Financial Statements'!J10 -> 0.096812797 | K9: =-'Financial Statements'!K15/'Financial Statements'!K10 -> 0.13083856 | L9: =-'Financial Statements'!L15/'Financial Statements'!L10 -> 0.079091229 | M9: =AVERAGE(H9:L9) -> 0.12512646 | N9: =M9 -> 0.12512646 | O9: =N9 -> 0.12512646 | P9: =O9 -> 0.12512646 | Q9: =P9 -> 0.12512646 | R9: =Q9 -> 0.12512646 | S9: =R9 -> 0.12512646 | T9: =S9 -> 0.12512646 | U9: =T9 -> 0.12512646 | V9: =U9 -> 0.12512646
D10: D&A expenses (% of PP&E) | F10: % | I10: =-'Financial Statements'!I17/'Working Schedules'!I14 -> 0.087686536 | J10: =-'Financial Statements'!J17/'Working Schedules'!J14 -> 0.078299504 | K10: =-'Financial Statements'!K17/'Working Schedules'!K14 -> 0.11124512 | L10: =-'Financial Statements'!L17/'Working Schedules'!L14 -> 0.082605063 | M10: =L10 -> 0.082605063 | N10: =M10 -> 0.082605063 | O10: =N10+2% -> 0.10260506 | P10: =O10 -> 0.10260506 | Q10: =P10 -> 0.10260506 | R10: =Q10+2% -> 0.12260506 | S10: =R10 -> 0.12260506 | T10: =S10 -> 0.12260506 | U10: =T10+2% -> 0.14260506 | V10: =U10 -> 0.14260506
D11: Interest (% of Debt) | F11: % | I11: =-'Financial Statements'!I19/'Working Schedules'!I20 -> 0.078566309 | J11: =-'Financial Statements'!J19/'Working Schedules'!J20 -> 0.075967592 | K11: =-'Financial Statements'!K19/'Working Schedules'!K20 -> 0.12789375 | L11: =-'Financial Statements'!L19/'Working Schedules'!L20 -> 0.094259031 | M11: =AVERAGE(H11:L11) -> 0.094171671 | N11: =M11 -> 0.094171671 | O11: =N11 -> 0.094171671 | P11: =O11 -> 0.094171671 | Q11: =P11 -> 0.094171671 | R11: =Q11 -> 0.094171671 | S11: =R11 -> 0.094171671 | T11: =S11 -> 0.094171671 | U11: =T11 -> 0.094171671 | V11: =U11 -> 0.094171671
D12: Other Income (Expenses) (% of Revenue) | F12: % | H12: ='Financial Statements'!H20/'Financial Statements'!H10 -> 0.005246319 | I12: ='Financial Statements'!I20/'Financial Statements'!I10 -> 0.0017245843 | J12: ='Financial Statements'!J20/'Financial Statements'!J10 -> 0.0033106212 | K12: ='Financial Statements'!K20/'Financial Statements'!K10 -> 0.025899195 | L12: ='Financial Statements'!L20/'Financial Statements'!L10 -> 0.0095159721 | M12: =AVERAGE(H12:L12) -> 0.0091393384 | N12: =M12 -> 0.0091393384 | O12: =N12 -> 0.0091393384 | P12: =O12 -> 0.0091393384 | Q12: =P12 -> 0.0091393384 | R12: =Q12 -> 0.0091393384 | S12: =R12 -> 0.0091393384 | T12: =S12 -> 0.0091393384 | U12: =T12 -> 0.0091393384 | V12: =U12 -> 0.0091393384
D13: Tax Rate (% of Profits before tax or EBT) | F13: % | H13: =-'Financial Statements'!H22/'Financial Statements'!H21 -> 0.083365141 | I13: =-'Financial Statements'!I22/'Financial Statements'!I21 -> 0.065561891 | J13: =-'Financial Statements'!J22/'Financial Statements'!J21 -> 0.30557091 | K13: =-'Financial Statements'!K22/'Financial Statements'!K21 -> 0.29055346 | L13: =-'Financial Statements'!L22/'Financial Statements'!L21 -> 0.26509762 | M13: =L13+0.5% -> 0.27009762 | N13: =M13 -> 0.27009762 | O13: =N13+0.5% -> 0.27509762 | P13: =O13 -> 0.27509762 | Q13: =P13+0.5% -> 0.28009762 | R13: =Q13 -> 0.28009762 | S13: =R13+0.5% -> 0.28509762 | T13: =S13 -> 0.28509762 | U13: =T13+0.5% -> 0.29009762 | V13: =U13 -> 0.29009762
D14: Dividends Payout | F14: % | H14: =-'Financial Statements'!H78/'Financial Statements'!H23 -> 0.065980083 | I14: =-'Financial Statements'!I78/'Financial Statements'!I23 -> 0.051928989 | J14: =-'Financial Statements'!J78/'Financial Statements'!J23 -> 0.027293106 | K14: =-'Financial Statements'!K78/'Financial Statements'!K23 -> 0.26605179 | L14: =-'Financial Statements'!L78/'Financial Statements'!L23 -> -0.17308225 | M14: =AVERAGE(H14:K14) -> 0.10281349 | N14: =M14 -> 0.10281349 | O14: =N14 -> 0.10281349 | P14: =O14 -> 0.10281349 | Q14: =P14 -> 0.10281349 | R14: =Q14 -> 0.10281349 | S14: =R14 -> 0.10281349 | T14: =S14 -> 0.10281349 | U14: =T14 -> 0.10281349 | V14: =U14 -> 0.10281349
D15: Account Receivables | F15: Days | H15: ='Financial Statements'!H31/'Financial Statements'!H10*365 -> 16.108597 | I15: ='Financial Statements'!I31/'Financial Statements'!I10*365 -> 24.92279 | J15: ='Financial Statements'!J31/'Financial Statements'!J10*365 -> 35.237489 | K15: ='Financial Statements'!K31/'Financial Statements'!K10*365 -> 40.607744 | L15: ='Financial Statements'!L31/'Financial Statements'!L10*365 -> 31.232115 | M15: =AVERAGE(H15:L15) -> 29.621747 | N15: =M15 -> 29.621747 | O15: =N15 -> 29.621747 | P15: =O15 -> 29.621747 | Q15: =P15 -> 29.621747 | R15: =Q15 -> 29.621747 | S15: =R15 -> 29.621747 | T15: =S15 -> 29.621747 | U15: =T15 -> 29.621747 | V15: =U15 -> 29.621747
D16: Days Inventory Outstanding (DIO) | F16: Days | H16: =-'Financial Statements'!H32/'Financial Statements'!H11*365 -> 291.95109 | I16: =-'Financial Statements'!I32/'Financial Statements'!I11*365 -> 303.21721 | J16: =-'Financial Statements'!J32/'Financial Statements'!J11*365 -> 92.869522 | K16: =-'Financial Statements'!K32/'Financial Statements'!K11*365 -> 187.27621 | L16: =-'Financial Statements'!L32/'Financial Statements'!L11*365 -> 164.58721 | M16: =AVERAGE(H16:L16) -> 207.98025 | N16: =M16 -> 207.98025 | O16: =N16 -> 207.98025 | P16: =O16 -> 207.98025 | Q16: =P16 -> 207.98025 | R16: =Q16 -> 207.98025 | S16: =R16 -> 207.98025 | T16: =S16 -> 207.98025 | U16: =T16 -> 207.98025 | V16: =U16 -> 207.98025
D17: Account Payables | F17: Days | H17: =-'Financial Statements'!H44/'Financial Statements'!H11*365 -> 54.011978 | I17: =-'Financial Statements'!I44/'Financial Statements'!I11*365 -> 91.297986 | J17: =-'Financial Statements'!J44/'Financial Statements'!J11*365 -> 39.688769 | K17: =-'Financial Statements'!K44/'Financial Statements'!K11*365 -> 71.428629 | L17: =-'Financial Statements'!L44/'Financial Statements'!L11*365 -> 36.995667 | M17: =AVERAGE(H17:L17) -> 58.684606 | N17: =M17 -> 58.684606 | O17: =N17 -> 58.684606 | P17: =O17 -> 58.684606 | Q17: =P17 -> 58.684606 | R17: =Q17 -> 58.684606 | S17: =R17 -> 58.684606 | T17: =S17 -> 58.684606 | U17: =T17 -> 58.684606 | V17: =U17 -> 58.684606
B19: Profitability Ratios
D20: Gross Margin % | F20: % | H20: ='Financial Statements'!H12/'Financial Statements'!H10 -> 0.28975939 | I20: ='Financial Statements'!I12/'Financial Statements'!I10 -> 0.28835132 | J20: ='Financial Statements'!J12/'Financial Statements'!J10 -> 0.25998739 | K20: ='Financial Statements'!K12/'Financial Statements'!K10 -> 0.25981318 | L20: ='Financial Statements'!L12/'Financial Statements'!L10 -> 0.17067574 | M20: ='Financial Statements'!M12/'Financial Statements'!M10 -> 0.2537174 | N20: ='Financial Statements'!N12/'Financial Statements'!N10 -> 0.2537174 | O20: ='Financial Statements'!O12/'Financial Statements'!O10 -> 0.2537174 | ... V20: ='Financial Statements'!V12/'Financial Statements'!V10 -> 0.2537174 | Y20: Gross margins held broadly stable between 26.0% and 29.0% across FY2021 to FY2024, before collapsing sharply to 17.1% in FY2025, the steepest single-year contraction in our model period. This compression was structurally driven: while our revenue fell 34.2% in FY2024 due to declining sugarcane output across Maharashtra and Karnataka per ICRA SY2025 data, our cane procurement costs remained sticky against state-mandated SAP obligations, creating a severe mismatch between revenue deflation and a near-rigid cost base. Our forecasts project a recovery and stabilization at 25.4% from FY2026F through FY2035F, underpinned by improving sugarcane availability per IBEF Agriculture November 2025 data alongside our industrial alcohol segment already demonstrating recovery in Q3 FY2026. The structural ceiling at 25.4% reflects the permanent reality that government-linked cane pricing grows independently of sugar price cycles.
D21: EBITDA Margin % | F21: % | H21: ='Financial Statements'!H16/'Financial Statements'!H10 -> 0.060624002 | I21: ='Financial Statements'!I16/'Financial Statements'!I10 -> 0.076170435 | J21: ='Financial Statements'!J16/'Financial Statements'!J10 -> 0.10754027 | K21: ='Financial Statements'!K16/'Financial Statements'!K10 -> 0.054967654 | L21: ='Financial Statements'!L16/'Financial Statements'!L10 -> 0.028727892 | M21: ='Financial Statements'!M16/'Financial Statements'!M10 -> 0.06560605 | N21: ='Financial Statements'!N16/'Financial Statements'!N10 -> 0.06560605 | O21: ='Financial Statements'!O16/'Financial Statements'!O10 -> 0.06560605 | ... V21: ='Financial Statements'!V16/'Financial Statements'!V10 -> 0.06560605 | Y21: EBITDA margin climbed from 6.1% in FY2021 to a peak of 10.8% in FY2023, capturing the operating leverage when national sugarcane output hit 490.5 MT per IBEF Agriculture data, driving both sugar volumes and distillery feedstock simultaneously. From that peak it deteriorated sharply to 5.5% in FY2024 and further to 2.9% in FY2025, as falling revenues collided with our fixed employee costs, finance charges, and depreciation on recently expanded distillery infrastructure, none of which moved with revenues. Our forecasts project recovery and stabilization at 6.6% from FY2026F through FY2035F, supported by our industrial alcohol segment delivering Rs. 65,063 Lakhs in nine month revenues per our Q3 FY2026 filing. The flat 6.6% across the entire forecast horizon reflects operating cost growth broadly neutralizing revenue benefits, keeping our EBITDA margin range-bound rather than structurally expanding.
D22: Operating Margin % | F22: % | H22: ='Financial Statements'!H18/'Financial Statements'!H10 -> 0.049508983 | I22: ='Financial Statements'!I18/'Financial Statements'!I10 -> 0.067350062 | J22: ='Financial Statements'!J18/'Financial Statements'!J10 -> 0.098221555 | K22: ='Financial Statements'!K18/'Financial Statements'!K10 -> 0.032198106 | L22: ='Financial Statements'!L18/'Financial Statements'!L10 -> 0.0091869997 | M22: ='Financial Statements'!M18/'Financial Statements'!M10 -> 0.045188082 | N22: ='Financial Statements'!N18/'Financial Statements'!N10 -> 0.044272723 | O22: ='Financial Statements'!O18/'Financial Statements'!O10 -> 0.038335235 | ... V22: ='Financial Statements'!V18/'Financial Statements'!V10 -> 0.032174501 | Y22: Operating margin rose from 5.0% in FY2021 to a peak of 9.8% in FY2023, before deteriorating sharply to 3.2% in FY2024 and collapsing to 0.9% in FY2025, the lowest in our model period. The sharper fall relative to EBITDA margin reveals that excise duty on sales of Rs. 2,331 Lakhs for 9M FY2026 and other manufacturing expenses created additional drag beyond what depreciation and finance costs alone explain. Our forecasts project a recovery to 4.5% in FY2026F before gradually declining toward 3.2% by FY2035F, reflecting our distillery segment transitioning into a maturity phase post India's achievement of the 20% ethanol blending target, compressing incremental operating profitability even as revenues continue growing steadily.
D23: Pretax margin % | F23: % | H23: ='Financial Statements'!H21/'Financial Statements'!H10 -> 0.016638538 | I23: ='Financial Statements'!I21/'Financial Statements'!I10 -> 0.035624456 | J23: ='Financial Statements'!J21/'Financial Statements'!J10 -> 0.076485034 | K23: ='Financial Statements'!K21/'Financial Statements'!K10 -> 0.023332717 | L23: ='Financial Statements'!L21/'Financial Statements'!L10 -> -0.015710459 | M23: ='Financial Statements'!M21/'Financial Statements'!M10 -> 0.017116516 | N23: ='Financial Statements'!N21/'Financial Statements'!N10 -> 0.019250705 | O23: ='Financial Statements'!O21/'Financial Statements'!O10 -> 0.015866761 | ... V23: ='Financial Statements'!V21/'Financial Statements'!V10 -> 0.019617469 | Y23: Our pretax margin moved from 1.7% in FY2021 to a peak of 7.6% in FY2023, before falling to 2.3% in FY2024 and swinging to -1.6% in FY2025, marking our first pretax loss year in the model period. The move into negative territory was a compounding effect where finance costs of Rs. 4,843 Lakhs for the full year FY2025 per our Annual Report, sitting on top of already compressed gross and operating margins, pushed us below breakeven entirely. Our Q4 FY2026 results showing a quarterly pretax profit of Rs. 1,612 Lakhs confirm the recovery is already underway. Our forecasts project pretax margin oscillating between 1.6% and 2.1% through FY2035F, reflecting persistent finance costs on distillery expansion debt partially offset by improving segment profitability across co-generation and industrial alcohol operations
D24: Net Margin % | F24: % | H24: ='Financial Statements'!H23/'Financial Statements'!H10 -> 0.015251464 | I24: ='Financial Statements'!I23/'Financial Statements'!I10 -> 0.033288849 | J24: ='Financial Statements'!J23/'Financial Statements'!J10 -> 0.053113433 | K24: ='Financial Statements'!K23/'Financial Statements'!K10 -> 0.016553315 | L24: ='Financial Statements'!L23/'Financial Statements'!L10 -> -0.011545654 | M24: ='Financial Statements'!M23/'Financial Statements'!M10 -> 0.012493386 | N24: ='Financial Statements'!N23/'Financial Statements'!N10 -> 0.014051136 | O24: ='Financial Statements'!O23/'Financial Statements'!O10 -> 0.011501853 | ... V24: ='Financial Statements'!V23/'Financial Statements'!V10 -> 0.013926488 | Y24: The Net margin rose from 1.5% in FY2021 to a peak of 5.3% in FY2023, the only year where revenue scale, operating leverage, and manageable finance costs aligned to deliver meaningful bottom line returns. It then deteriorated to 1.7% in FY2024 and turned negative at -1.2% in FY2025, where our full year PAT loss of Rs. 1,624.95 Lakhs per our Annual Report FY2024-25 left the bottom line fully exposed to the cost-revenue mismatch. Our Q4 FY2026 quarterly PAT recovery of Rs. 1,375.79 Lakhs per our December 2025 filing confirms the turnaround is real. Our forecasts project net margin oscillating between 1.2% and 1.5% through FY2035F, reflecting that persistently elevated finance costs on distillery expansion debt will continue consuming a disproportionate share of operating profits, leaving structurally thin but stable bottom line returns across the forecast horizon.
C26: Liquidity Ratios
D27: Current Ratio | F27: Times | H27: =SUM('Financial Statements'!H29:H33)/SUM('Financial Statements'!H44:H45) -> 3.0743343 | I27: =SUM('Financial Statements'!I29:I33)/SUM('Financial Statements'!I44:I45) -> 2.3705198 | J27: =SUM('Financial Statements'!J29:J33)/SUM('Financial Statements'!J44:J45) -> 1.8995365 | K27: =SUM('Financial Statements'!K29:K33)/SUM('Financial Statements'!K44:K45) -> 2.2645649 | L27: =SUM('Financial Statements'!L29:L33)/SUM('Financial Statements'!L44:L45) -> 2.4524123 | M27: =SUM('Financial Statements'!M29:M33)/SUM('Financial Statements'!M44:M45) -> 2.0851183 | N27: =SUM('Financial Statements'!N29:N33)/SUM('Financial Statements'!N44:N45) -> 1.9648182 | O27: =SUM('Financial Statements'!O29:O33)/SUM('Financial Statements'!O44:O45) -> 1.882528 | ... V27: =SUM('Financial Statements'!V29:V33)/SUM('Financial Statements'!V44:V45) -> 1.8912961 | Y27: The current ratio stood at a comfortable 3.1x in FY2021, declining steadily to 1.9x in FY2023 before recovering to 2.3x in FY2024 and 2.5x in FY2025, reflecting the seasonal inventory buildup during crushing periods that inflates our current asset base. The 2.5x reading however masks an important underlying reality, our Q2 FY2026 balance sheet shows current assets dropping sharply to Rs. 37,410 Lakhs from Rs. 72,375 Lakhs at FY2025 year end as seasonal inventory drawdowns compress the numerator during off-crushing periods. Our forecasts project current ratio moderating from 2.1x in FY2026F and stabilizing between 1.8x and 2.0x through FY2035F, reflecting increasing short term borrowing requirements to fund our expanded distillery operations progressively tightening our short term liquidity headroom.
D28: Quick Ratio | F28: Times | H28: =SUM('Financial Statements'!H29:H31,'Financial Statements'!H33)/SUM('Financial Statements'!H44:H45) -> 0.48948683 | I28: =SUM('Financial Statements'!I29:I31,'Financial Statements'!I33)/SUM('Financial Statements'!I44:I45) -> 0.39388483 | J28: =SUM('Financial Statements'!J29:J31,'Financial Statements'!J33)/SUM('Financial Statements'!J44:J45) -> 0.8059246 | K28: =SUM('Financial Statements'!K29:K31,'Financial Statements'!K33)/SUM('Financial Statements'!K44:K45) -> 0.7595285 | L28: =SUM('Financial Statements'!L29:L31,'Financial Statements'!L33)/SUM('Financial Statements'!L44:L45) -> 0.66900132 | M28: =SUM('Financial Statements'!M29:M31,'Financial Statements'!M33)/SUM('Financial Statements'!M44:M45) -> 0.27048233 | N28: =SUM('Financial Statements'!N29:N31,'Financial Statements'!N33)/SUM('Financial Statements'!N44:N45) -> 0.074590124 | O28: =SUM('Financial Statements'!O29:O31,'Financial Statements'!O33)/SUM('Financial Statements'!O44:O45) -> -0.076017071 | ... V28: =SUM('Financial Statements'!V29:V31,'Financial Statements'!V33)/SUM('Financial Statements'!V44:V45) -> -0.38683387 | Y28: Quick ratio remained range-bound between 0.4x and 0.8x across FY2021 to FY2025, consistently below 1.0x throughout our entire operating history, confirming that without liquidating inventory we cannot fully cover short term obligations at any point, a structurally expected position for a sugar company where finished goods represent the single largest current asset per our Q2 FY2026 balance sheet showing inventories of Rs. 15,128 Lakhs against total current assets of Rs. 37,410 Lakhs. Our forecasts show quick ratio deteriorating from 0.3x in FY2026F into negative territory from FY2028F onwards, reaching -0.4x by FY2035F, driven by rising short term borrowings funding our industrial alcohol expansion outpacing liquid asset growth, signaling investors must closely monitor our seasonal borrowing patterns and working capital management in future quarters.
D29: Cash Cycle | F29: Days | H29: =H15+H16-H17 -> 254.04771 | I29: =I15+I16-I17 -> 236.84201 | J29: =J15+J16-J17 -> 88.418242 | K29: =K15+K16-K17 -> 156.45532 | L29: =L15+L16-L17 -> 158.82366 | M29: =M15+M16-M17 -> 178.91739 | N29: =N15+N16-N17 -> 178.91739 | O29: =O15+O16-O17 -> 178.91739 | ... V29: =V15+V16-V17 -> 178.91739 | Y29: The Cash cycle swung dramatically from 254.0 days in FY2021 to a low of 88.4 days in FY2023, the peak sugarcane output year where strong industrial alcohol offtake rapidly converted molasses inventory into cash, before widening again to 156.5 days in FY2024 and 158.8 days in FY2025 as slower sugar release quotas and normalized ethanol offtake extended our working capital cycle. Our Q3 FY2026 nine month revenues of Rs. 1,11,807 Lakhs alongside recovering industrial alcohol segment profits of Rs. 3,702 Lakhs confirm the business is operating at improved throughput. Our forecasts project cash cycle stabilizing at 178.9 days from FY2026F through FY2035F, reflecting normalized seasonal inventory holding as sugarcane crushing volumes recover per IBEF Agriculture November 2025 data, though this elongation relative to the FY2023 low signals structurally higher working capital intensity as distillery operations scale up alongside sugar.
C31: Leverage Ratios
D32: Debt/Equity Ratio | F32: Times | H32: ='Financial Statements'!H47/'Financial Statements'!H53 -> 6.8839986 | I32: ='Financial Statements'!I47/'Financial Statements'!I53 -> 5.2535372 | J32: ='Financial Statements'!J47/'Financial Statements'!J53 -> 1.5721441 | K32: ='Financial Statements'!K47/'Financial Statements'!K53 -> 2.1868428 | L32: ='Financial Statements'!L47/'Financial Statements'!L53 -> 2.8285949 | M32: ='Financial Statements'!M47/'Financial Statements'!M53 -> 2.6184907 | N32: ='Financial Statements'!N47/'Financial Statements'!N53 -> 2.4000882 | O32: ='Financial Statements'!O47/'Financial Statements'!O53 -> 2.2351539 | ... V32: ='Financial Statements'!V47/'Financial Statements'!V53 -> 1.3065106 | Y32: Debt/Equity ratio tells a compelling deleveraging story across the audited years, falling sharply from 6.9x in FY2021 to just 1.6x in FY2023, driven by strong profitability compounding our retained earnings base while we simultaneously repaid short term borrowings during the peak sugarcane cycle. It reversed to 2.2x in FY2024 and 2.8x in FY2025 as consecutive net losses eroded our equity base, our Annual Report FY2024-25 confirming other equity declining to Rs. 20,475 Lakhs while distillery expansion debt remained on our books. Our forecasts project a steady and encouraging deleveraging from 2.6x in FY2026F toward 1.3x by FY2035F, reflecting that as profitability gradually recovers and retained earnings rebuild our equity base, our balance sheet will progressively strengthen over the forecast horizon.
D33: Asset/Equity Ratio | F33: Times | H33: ='Financial Statements'!H40/'Financial Statements'!H53 -> 11.098491 | I33: ='Financial Statements'!I40/'Financial Statements'!I53 -> 9.5567113 | J33: ='Financial Statements'!J40/'Financial Statements'!J53 -> 4.1496225 | K33: ='Financial Statements'!K40/'Financial Statements'!K53 -> 4.6187155 | L33: ='Financial Statements'!L40/'Financial Statements'!L53 -> 5.2343558 | M33: ='Financial Statements'!M40/'Financial Statements'!M53 -> 5.2079355 | N33: ='Financial Statements'!N40/'Financial Statements'!N53 -> 4.9220207 | O33: ='Financial Statements'!O40/'Financial Statements'!O53 -> 4.7122268 | ... V33: ='Financial Statements'!V40/'Financial Statements'!V53 -> 3.3832665 | Y33: The Asset/Equity ratio declined from 11.1x in FY2021 to 4.1x in FY2023, mirroring the equity accretion during our peak profitability years as retained earnings meaningfully strengthened our net worth relative to our asset base. From FY2024 it reversed to 4.6x and 5.2x in FY2025, as loss-driven equity erosion inflated the multiple without any meaningful change in our absolute asset base, our Q2 FY2026 balance sheet showing total assets of Rs. 78,379 Lakhs against equity of only Rs. 17,159 Lakhs confirming this dynamic. Our forecasts project asset/equity declining steadily from 5.2x in FY2026F toward 3.4x by FY2035F, reflecting gradual equity rebuilding through retained profits as our three segment operations deliver improving but structurally thin margins over the long term.
D34: Debt/Capital Ratio | F34: Times | H34: ='Financial Statements'!H47/('Financial Statements'!H47+'Financial Statements'!H53) -> 0.87316081 | I34: ='Financial Statements'!I47/('Financial Statements'!I47+'Financial Statements'!I53) -> 0.8400905 | J34: ='Financial Statements'!J47/('Financial Statements'!J47+'Financial Statements'!J53) -> 0.61121929 | K34: ='Financial Statements'!K47/('Financial Statements'!K47+'Financial Statements'!K53) -> 0.68620981 | L34: ='Financial Statements'!L47/('Financial Statements'!L47+'Financial Statements'!L53) -> 0.73880757 | M34: ='Financial Statements'!M47/('Financial Statements'!M47+'Financial Statements'!M53) -> 0.72364168 | N34: ='Financial Statements'!N47/('Financial Statements'!N47+'Financial Statements'!N53) -> 0.70588998 | O34: ='Financial Statements'!O47/('Financial Statements'!O47+'Financial Statements'!O53) -> 0.69089569 | ... V34: ='Financial Statements'!V47/('Financial Statements'!V47+'Financial Statements'!V53) -> 0.56644466 | Y34: Our debt/capital ratio declined from 0.9x in FY2021 to 0.6x in FY2023 during our peak deleveraging phase, before stabilizing at 0.7x through FY2024 and FY2025, suggesting that while equity erosion from consecutive losses was real, our absolute debt levels did not expand dramatically enough to materially worsen our capital structure. This is confirmed by our Q2 FY2026 cash flow statement showing net short term borrowing repayments of Rs. 16,469 Lakhs during the half year, demonstrating active debt management even through the downturn. Our forecasts project debt/capital remaining at 0.7x through FY2030F before gradually easing to 0.6x by FY2031F through FY2035F, reflecting a capital structure finding its natural equilibrium where distillery expansion debt and seasonal sugar borrowings together consistently represent the majority of our total capital employed.
C36: DuPont/Earning Power
D37: Asset Turnover Ratio | F37: Times | I37: ='Financial Statements'!I10/AVERAGE('Financial Statements'!H40:I40) -> 1.2654752 | J37: ='Financial Statements'!J10/AVERAGE('Financial Statements'!I40:J40) -> 1.8655037 | K37: ='Financial Statements'!K10/AVERAGE('Financial Statements'!J40:K40) -> 1.2761964 | L37: ='Financial Statements'!L10/AVERAGE('Financial Statements'!K40:L40) -> 1.2702983 | M37: ='Financial Statements'!M10/AVERAGE('Financial Statements'!L40:M40) -> 1.3182999 | N37: ='Financial Statements'!N10/AVERAGE('Financial Statements'!M40:N40) -> 1.3647995 | O37: ='Financial Statements'!O10/AVERAGE('Financial Statements'!N40:O40) -> 1.4327383 | P37: ='Financial Statements'!P10/AVERAGE('Financial Statements'!O40:P40) -> 1.4940051 | ... V37: ='Financial Statements'!V10/AVERAGE('Financial Statements'!U40:V40) -> 1.7005494 | Y37: Asset turnover stood at 1.3x in FY2022, peaked at 1.9x in FY2023 reflecting the high revenue environment when national sugarcane output hit 490.5 MT per IBEF Agriculture data, before declining back to 1.3x in both FY2024 and FY2025 as revenue contraction outpaced any reduction in our asset base. Our significant capital work in progress of Rs. 10,834 Lakhs visible in our Q2 FY2026 balance sheet means our denominator continues growing even when revenues compress, mechanically suppressing turnover. Our forecasts project asset turnover gradually improving from 1.3x in FY2026F toward 1.7x by FY2035F, reflecting that incremental revenue growth from our maturing ethanol and co-generation segments will progressively outpace incremental asset additions as our capital expansion phase winds down.
D38: Pre-Tax ROA | F38: % | I38: ='Financial Statements'!I21/AVERAGE('Financial Statements'!H40:I40) -> 0.045081865 | J38: ='Financial Statements'!J21/AVERAGE('Financial Statements'!I40:J40) -> 0.14268311 | K38: ='Financial Statements'!K21/AVERAGE('Financial Statements'!J40:K40) -> 0.029777129 | L38: ='Financial Statements'!L21/AVERAGE('Financial Statements'!K40:L40) -> -0.019956971 | M38: ='Financial Statements'!M21/AVERAGE('Financial Statements'!L40:M40) -> 0.022564701 | N38: ='Financial Statements'!N21/AVERAGE('Financial Statements'!M40:N40) -> 0.026273352 | O38: ='Financial Statements'!O21/AVERAGE('Financial Statements'!N40:O40) -> 0.022732917 | P38: ='Financial Statements'!P21/AVERAGE('Financial Statements'!O40:P40) -> 0.026908048 | ... V38: ='Financial Statements'!V21/AVERAGE('Financial Statements'!U40:V40) -> 0.033360476 | Y38: Pre-tax ROA stood at 5% in FY2022, peaking at 14% in FY2023 during the high revenue sugarcane cycle before collapsing to 3.0% in FY2024 and turning negative at -2.0% in FY2025, directly mirroring the pretax margin deterioration compounded by our expanding asset base from distillery investments. Our Q4 FY2026 quarterly pretax profit of Rs. 1,612 Lakhs signals the return to positive territory. Our forecasts project pre-tax ROA oscillating between 2.3% and 3.4% through FY2035F, reflecting the fundamental tension where an asset heavy balance sheet demands returns that our structurally thin pretax margins, constrained by government linked cane pricing and elevated finance costs, can only partially deliver.
D39: Pre-Tax ROE | F39: % | I39: ='Financial Statements'!I21/AVERAGE('Financial Statements'!H53:I53) -> 0.4584977 | J39: ='Financial Statements'!J21/AVERAGE('Financial Statements'!I53:J53) -> 0.86628013 | K39: ='Financial Statements'!K21/AVERAGE('Financial Statements'!J53:K53) -> 0.13076453 | L39: ='Financial Statements'!L21/AVERAGE('Financial Statements'!K53:L53) -> -0.098060355 | M39: ='Financial Statements'!M21/AVERAGE('Financial Statements'!L53:M53) -> 0.11780209 | N39: ='Financial Statements'!N21/AVERAGE('Financial Statements'!M53:N53) -> 0.1329105 | O39: ='Financial Statements'!O21/AVERAGE('Financial Statements'!N53:O53) -> 0.10942242 | P39: ='Financial Statements'!P21/AVERAGE('Financial Statements'!O53:P53) -> 0.12353841 | ... V39: ='Financial Statements'!V21/AVERAGE('Financial Statements'!U53:V53) -> 0.11533317 | Y39: Our pre-tax ROE climbed from 46% in FY2022 to an exceptional 87% in FY2023, the single year where strong sugarcane volumes, expanding distillery revenues, and a still-thin equity base from our deleveraging phase combined to deliver an outsized return on shareholder equity. From that peak it collapsed to 13% in FY2024 and turned negative at -10% in FY2025, as back to back pretax losses eroded returns while our equity base simultaneously declined from retained loss accumulation, creating a double compression on the ratio. Our forecasts project pre-tax ROE stabilizing between 11% and 13% through FY2035F, reflecting that as our equity base gradually rebuilds through retained profits, the denominator expansion will structurally moderate returns even as pretax profitability recovers.
D40: Tax Complement | F40: % | H40: =1-H13 -> 0.91663486 | I40: =1-I13 -> 0.93443811 | J40: =1-J13 -> 0.69442909 | K40: =1-K13 -> 0.70944654 | L40: =1-L13 -> 0.73490238 | M40: =1-M13 -> 0.72990238 | N40: =1-N13 -> 0.72990238 | O40: =1-O13 -> 0.72490238 | ... V40: =1-V13 -> 0.70990238 | Y40: The Tax complement remained elevated between 92% and 93% across FY2021 to FY2022, reflecting that deferred tax adjustments and carried forward losses absorbed our tax liability almost entirely during those years. It dropped to 69% in FY2023 as strong pretax profits finally exhausted our loss shield, before recovering to 71% in FY2024 and 73% in FY2025 as deferred tax movements per our quarterly filings partially offset the liability during the downturn. Our forecasts project tax complement holding at 73% through FY2027F before stepping down to 72% from FY2028F and gradually declining toward 71% by FY2032F through FY2035F, reflecting progressive depletion of our deferred tax shields as the business sustains consistent profitability over the forecast horizon.
D41: ROE | I41: ='Financial Statements'!I23/AVERAGE('Financial Statements'!H53:I53) -> 0.42843773 | J41: ='Financial Statements'!J23/AVERAGE('Financial Statements'!I53:J53) -> 0.60157013 | K41: ='Financial Statements'!K23/AVERAGE('Financial Statements'!J53:K53) -> 0.092770443 | L41: ='Financial Statements'!L23/AVERAGE('Financial Statements'!K53:L53) -> -0.072064788 | M41: ='Financial Statements'!M23/AVERAGE('Financial Statements'!L53:M53) -> 0.085984028 | N41: ='Financial Statements'!N23/AVERAGE('Financial Statements'!M53:N53) -> 0.09701169 | O41: ='Financial Statements'!O23/AVERAGE('Financial Statements'!N53:O53) -> 0.079320574 | P41: ='Financial Statements'!P23/AVERAGE('Financial Statements'!O53:P53) -> 0.089553286 | ... V41: ='Financial Statements'!V23/AVERAGE('Financial Statements'!U53:V53) -> 0.081875292 | Y41: ROE rose from 43% in FY2022 to 60% in FY2023, driven by the same thin equity base and peak earnings combination that inflated our pre-tax ROE, before collapsing to 9% in FY2024 and turning negative at -7% in FY2025 as our PAT loss of Rs. 1,624.95 Lakhs per our Annual Report FY2024-25 eroded the equity base it was being measured against from both ends simultaneously. Our Q4 FY2026 quarterly PAT of Rs. 1,375.79 Lakhs per our December 2025 filing confirms the return to positive earnings. Our forecasts project ROE oscillating between 7% and 10% through FY2035F, reflecting that while earnings recover, our gradually rebuilding equity base will mechanically moderate the ratio, leaving shareholders with stable but structurally compressed returns relative to the peak cycle years.
D42: Equity Retention | F42: % | H42: =1-H14 -> 0.93401992 | I42: =1-I14 -> 0.94807101 | J42: =1-J14 -> 0.97270689 | K42: =1-K14 -> 0.73394821 | L42: =1-L14 -> 1.1730822 | M42: =1-M14 -> 0.89718651 | N42: =1-N14 -> 0.89718651 | O42: =1-O14 -> 0.89718651 | ... V42: =1-V14 -> 0.89718651 | Y42: The Equity retention remained consistently high between 93% and 97% across FY2021 to FY2023, reflecting our conservative dividend policy prioritizing internal capital retention for distillery expansion over shareholder distribution. It dropped to 73% in FY2024 as minimal earnings made even a modest dividend consume a larger share of profits, before jumping to 117% in FY2025, a mathematical artifact where retained losses exceeded earnings, confirmed by our other equity declining to Rs. 20,475 Lakhs per our Annual Report FY2024-25. Our forecasts project equity retention stabilizing at 90% from FY2026F through FY2035F, reflecting our strategic intent to continue prioritizing debt servicing and working capital retention over dividend distribution as our industrial alcohol segment scales up.
D43: Reinvestment Rate | F43: % | I43: =('Financial Statements'!H23+'Financial Statements'!H78)/AVERAGE('Financial Statements'!H53:I53) -> 0.15747472 | J43: =('Financial Statements'!I23+'Financial Statements'!I78)/AVERAGE('Financial Statements'!I53:J53) -> 0.23980609 | K43: =('Financial Statements'!J23+'Financial Statements'!J78)/AVERAGE('Financial Statements'!J53:K53) -> 0.43981988 | L43: =('Financial Statements'!K23+'Financial Statements'!K78)/AVERAGE('Financial Statements'!K53:L53) -> 0.068818447 | M43: =('Financial Statements'!L23+'Financial Statements'!L78)/AVERAGE('Financial Statements'!L53:M53) -> -0.084845602 | N43: =('Financial Statements'!M23+'Financial Statements'!M78)/AVERAGE('Financial Statements'!M53:N53) -> 0.071046128 | O43: =('Financial Statements'!N23+'Financial Statements'!N78)/AVERAGE('Financial Statements'!N53:O53) -> 0.080439902 | P43: =('Financial Statements'!O23+'Financial Statements'!O78)/AVERAGE('Financial Statements'!O53:P53) -> 0.065959411 | ... V43: =('Financial Statements'!U23+'Financial Statements'!U78)/AVERAGE('Financial Statements'!U53:V53) -> 0.062444372 | Y43: Reinvestment rate stood at 16% in FY2022, rising to 24% in FY2023 and peaking at 44% in FY2024 as we aggressively deployed capital into distillery infrastructure even through the revenue downturn, before collapsing to 7% in FY2025 as losses left minimal earnings available for reinvestment. Our forecasts project reinvestment rate turning negative at -8% in FY2026F before recovering and stabilizing between 6% and 8% through FY2035F, reflecting that as our distillery infrastructure matures and ethanol blending targets are achieved per IBEF Food Processing November 2025 data, incremental reinvestment needs will structurally diminish, transitioning our capital allocation story from aggressive expansion toward maintenance and optimization.
C45: Operating Ratios
D46: AR Turnover | F46: Times | H46: =365/H15 -> 22.658708 | I46: =365/I15 -> 14.64523 | J46: =365/J15 -> 10.358286 | K46: =365/K15 -> 8.9884333 | L46: =365/L15 -> 11.686688 | M46: =365/M15 -> 12.322028 | N46: =365/N15 -> 12.322028 | O46: =365/O15 -> 12.322028 | ... V46: =365/V15 -> 12.322028 | Y46: The Accounts receivable turnover declined steadily from 22.7x in FY2021 to a low of 9.0x in FY2024, reflecting the period where slower OMC payment cycles for ethanol offtake and subdued sugar demand stretched our collection timelines as revenues simultaneously contracted. It recovered to 11.7x in FY2025 as industrial alcohol collections normalized, consistent with our Q3 FY2026 nine month revenues of Rs. 1,11,807 Lakhs demonstrating stronger offtake momentum from Oil Marketing Companies under India's structured ethanol blending program per IBEF Food Processing November 2025 data. Our forecasts project AR turnover stabilizing at 12.3x from FY2026F through FY2035F, reflecting mature and predictable collection cycles as ethanol blending commitments provide contractual payment regularity across our three operating segments.
D47: Inventory Turnover | F47: Times | H47: =365/H16 -> 1.2502094 | I47: =365/I16 -> 1.2037575 | J47: =365/J16 -> 3.9302453 | K47: =365/K16 -> 1.9489929 | L47: =365/L16 -> 2.2176693 | M47: =365/M16 -> 1.7549744 | N47: =365/N16 -> 1.7549744 | O47: =365/O16 -> 1.7549744 | ... V47: =365/V16 -> 1.7549744 | Y47: Inventory turnover swung dramatically from 1.3x in FY2021 to a peak of 3.9x in FY2023 during peak sugarcane output, before falling back to 1.9x in FY2024 and recovering to 2.2x in FY2025 as our distillery segment accelerated molasses conversion into industrial alcohol. This volatility is structurally embedded in our business model, our Q2 FY2026 balance sheet showing inventories collapsing from Rs. 52,631 Lakhs at FY2025 year end to just Rs. 15,128 Lakhs mid-year confirms how dramatically crushing seasonality swings our stock levels. Our forecasts project inventory turnover stabilizing at 1.8x from FY2026F through FY2035F, reflecting normalized seasonal inventory holding as sugarcane crushing volumes recover per ICRA's July 2025 projection of a 15% production rebound in SY2026.
D48: AP Turnover | F48: Times | H48: =365/H17 -> 6.7577603 | I48: =365/I17 -> 3.9978976 | J48: =365/J17 -> 9.1965563 | K48: =365/K17 -> 5.1099959 | L48: =365/L17 -> 9.8660203 | M48: =365/M17 -> 6.2196891 | N48: =365/N17 -> 6.2196891 | O48: =365/O17 -> 6.2196891 | ... V48: =365/V17 -> 6.2196891 | Y48: Accounts payable turnover fluctuated between 4.0x and 9.9x across FY2021 to FY2025, directly mirroring the rhythm of our state-mandated cane payment obligations to farmers under SAP timelines, where crushing season intensification rapidly accumulates payables before systematic discharge. The 9.9x in FY2025 is particularly notable, our Q3 FY2026 sugar segment liabilities jumping to Rs. 22,140 Lakhs from Rs. 7,704 Lakhs in Q2 FY2026 confirms that as the new crushing season commenced in November 2025 per our quarterly filing notes, cane payment obligations accumulated rapidly. Our forecasts project AP turnover stabilizing at 6.2x from FY2026F through FY2035F, reflecting normalized cane procurement payment cycles as sugarcane availability recovers across our Ugarkhurd and Jewargi units.
D49: ROIC | F49: % | H49: ='Financial Statements'!H23/SUM('Financial Statements'!H53:H54,'Financial Statements'!H47) -> 0.026865677 | I49: ='Financial Statements'!I23/SUM('Financial Statements'!I53:I54,'Financial Statements'!I47) -> 0.05690281 | J49: ='Financial Statements'!J23/SUM('Financial Statements'!J53:J54,'Financial Statements'!J47) -> 0.18141682 | K49: ='Financial Statements'!K23/SUM('Financial Statements'!K53:K54,'Financial Statements'!K47) -> 0.028234935 | L49: ='Financial Statements'!L23/SUM('Financial Statements'!L53:L54,'Financial Statements'!L47) -> -0.019649189 | M49: ='Financial Statements'!M23/SUM('Financial Statements'!M53:M54,'Financial Statements'!M47) -> 0.022879882 | N49: ='Financial Statements'!N23/SUM('Financial Statements'!N53:N54,'Financial Statements'!N47) -> 0.02734221 | O49: ='Financial Statements'!O23/SUM('Financial Statements'!O53:O54,'Financial Statements'!O47) -> 0.02367588 | ... V49: ='Financial Statements'!V23/SUM('Financial Statements'!V53:V54,'Financial Statements'!V47) -> 0.034239884 | Y49: ROIC stood at a modest 2.7% in FY2021, rising to 5.7% in FY2022 and peaking sharply at 18.1% in FY2023, the single year where capital deployed across sugar, co-generation, and our nascent distillery operations simultaneously generated exceptional returns during the peak sugarcane cycle. It collapsed to 2.8% in FY2024 and turned negative at -2.0% in FY2025 as operating losses consumed invested capital returns entirely, our significant PP&E of Rs. 27,542 Lakhs per our Q2 FY2026 balance sheet continuing to expand our invested capital base even through the downturn. Our forecasts project ROIC recovering to 2.3% in FY2026F and gradually improving toward 3.4% by FY2035F, reflecting that as our distillery infrastructure matures and incremental capex requirements diminish, our thin but recovering net margins will progressively generate better returns against a more stable invested capital base.
D52: Back to Cover

Sheet Market_Returns
B2: Date | C2: Index Closing Price | E2: Index | F2: Nifty 50 Total Return Index
B4: 46118 | C4: 34615.19 | E4: Yearfrac | F4: =YEARFRAC(B4,B2476) -> 10.002778
B5: 46114 | C5: 34230.63 | E5: Market Returns | F5: =_xlfn.RRI(F4,C2476,C4) -> 0.13054079
B6: 46113 | C6: 34179.9
B7: 46111 | C7: 33655.43 | E7: 10Y Risk free Rate (Bond Yield) | F7: 0.06961
B8: 46108 | C8: 34391.13 | E8: (10 Year Indian-bond yield)
B9: 46106 | C9: 35124.87
B10: 46105 | C10: 34530.99 | E10: Back to Cover
B11: 46104 | C11: 33928.59
B12: 46101 | C12: 34835.63
B13: 46100 | C13: 34666.28
B14: 46099 | C14: 35835.24
B15: 46098 | C15: 35538.92
B16: 46097 | C16: 35279.17
B17: 46094 | C17: 34890.78
B18: 46093 | C18: 35626.27
B19: 46092 | C19: 35969.45
B20: 46091 | C20: 36564.4
B21: 46090 | C21: 36212.4
B22: 46087 | C22: 36848.97
... B2476: 42465 | C2476: 10145.1

Sheet WACC
A1: Ugar Sugar Works Ltd.
A2: Weighted-Average Cost of Capital (WACC)
A4: Comparable Companies Beta
D6: Name | H6: Equity Value | I6: Total Debt | J6: Debt/ Equity | K6: Debt/ Capital | L6: Tax Rate % | M6: Levered Beta | N6: Unlevered Beta
D7: ='Comps Valuation'!D8 -> Mawana Sugars Limited | F7: ='Financial Statements'!F10 -> ₹ in Lakhs | H7: ='Comps Valuation'!J8 -> 31097.907 | I7: ='Comps Valuation'!K8 -> 19559.408 | J7: =I7/H7 -> 0.6289622 | K7: =I7/(H7+I7) -> 0.38611221 | L7: ='Comps Valuation'!Q8 -> 0.164934 | M7: 0.07 | N7: =M7/(1+J7*(1-L7)) -> 0.045894869
D8: ='Comps Valuation'!D9 -> DCM Shriram Industries Limited | H8: ='Comps Valuation'!J9 -> 32700.362 | I8: ='Comps Valuation'!K9 -> 57177.206 | J8: =I8/H8 -> 1.748519 | K8: =I8/(H8+I8) -> 0.6361677 | L8: ='Comps Valuation'!Q9 -> 0.354496 | M8: 0.08 | N8: =M8/(1+J8*(1-L8)) -> 0.037582046
D9: ='Comps Valuation'!D10 -> Magadh Sugar & Energy Limited | H9: ='Comps Valuation'!J10 -> 58874.83 | I9: ='Comps Valuation'!K10 -> 75737.668 | J9: =I9/H9 -> 1.2864185 | K9: =I9/(H9+I9) -> 0.56263474 | L9: ='Comps Valuation'!Q10 -> 0.256562 | M9: 0.12 | N9: =M9/(1+J9*(1-L9)) -> 0.061338016
D10: ='Comps Valuation'!D11 -> Dwarikesh Sugar Industries Limited | H10: ='Comps Valuation'!J11 -> 61760.98 | I10: ='Comps Valuation'!K11 -> 54311.716 | J10: =I10/H10 -> 0.87938559 | K10: =I10/(H10+I10) -> 0.46791121 | L10: ='Comps Valuation'!Q11 -> 0.564909 | M10: 0.24 | N10: =M10/(1+J10*(1-L10)) -> 0.1735844
D11: ='Comps Valuation'!D12 -> Avadh Sugar & Energy Limited | H11: ='Comps Valuation'!J12 -> 64529.377 | I11: ='Comps Valuation'!K12 -> 146798.27 | J11: =I11/H11 -> 2.274906 | K11: =I11/(H11+I11) -> 0.69464772 | L11: ='Comps Valuation'!Q12 -> 0.35483 | M11: 0.29 | N11: =M11/(1+J11*(1-L11)) -> 0.11751828
D12: ='Comps Valuation'!D13 -> Davangere Sugar Company Limited | H12: ='Comps Valuation'!J13 -> 46392.038 | I12: ='Comps Valuation'!K13 -> 38172.128 | J12: =I12/H12 -> 0.82281636 | K12: =I12/(H12+I12) -> 0.45139838 | L12: ='Comps Valuation'!Q13 -> 0.145261 | M12: 0.77 | N12: =M12/(1+J12*(1-L12)) -> 0.45206544
D13: ='Comps Valuation'!D14 -> Dhampur Sugar Mills Limited | H13: ='Comps Valuation'!J14 -> 72794.968 | I13: ='Comps Valuation'!K14 -> 100215.12 | J13: =I13/H13 -> 1.3766765 | K13: =I13/(H13+I13) -> 0.57924438 | L13: ='Comps Valuation'!Q14 -> 0.302683 | M13: 0.52 | N13: =M13/(1+J13*(1-L13)) -> 0.26530884
D14: ='Comps Valuation'!D15 -> Uttam Sugar Mills Limited | H14: ='Comps Valuation'!J15 -> 79594.256 | I14: ='Comps Valuation'!K15 -> 28639.377 | J14: =I14/H14 -> 0.35981713 | K14: =I14/(H14+I14) -> 0.264607 | L14: ='Comps Valuation'!Q15 -> 0.265864 | M14: 0.41 | N14: =M14/(1+J14*(1-L14)) -> 0.32432739
D15: Average | J15: =AVERAGE(J7:J14) -> 1.1721877 | K15: =AVERAGE(K7:K14) -> 0.50534042 | L15: =AVERAGE(L7:L14) -> 0.30119238 | M15: =AVERAGE(M7:M14) -> 0.3125 | N15: =AVERAGE(N7:N14) -> 0.18470241
D16: Median | J16: =MEDIAN(J7:J14) -> 1.082902 | K16: =MEDIAN(K7:K14) -> 0.51527298 | L16: =MEDIAN(L7:L14) -> 0.2842735 | M16: =MEDIAN(M7:M14) -> 0.265 | N16: =MEDIAN(N7:N14) -> 0.14555134
D18: ='Comps Valuation'!D20 -> The Ugar Sugar Works Limited | F18: =F7 -> ₹ in Lakhs | H18: ='Comps Valuation'!J20 -> 44258.298 | I18: ='Comps Valuation'!K20 -> 45440.079
C20: WACC Calculation
C22: Target Capital structure
D23: Proportion of Debt | H23: =K16 -> 0.51527298
D24: Proportion of Equity | H24: =1-H23 -> 0.48472702
C26: Current Capital Structure
D27: Market Cap | H27: =H18 -> 44258.298
D28: Total Debt | H28: =I18 -> 45440.079
D29: Debt/Equity | H29: =I18/H18 -> 1.0267019
C31: Cost of Debt
D32: Pre-tax Cost of Debt | H32: ='Ratio Analysis & Interpretation'!M11 -> 0.094171671
D33: Tax Rate | H33: ='Comps Valuation'!Q20 -> 0.27409762
D34: After Tax Cost of Debt | H34: =H32*(1-H33) -> 0.06835944
C36: Cost of Equity
D37: Risk Free Rate | H37: =Market_Returns!F7 -> 0.06961
D38: Equity Market Return | H38: =Market_Returns!F5 -> 0.13054079
D39: Equity Risk Premium | H39: =H38-H37 -> 0.060930792
D40: Levered Equity Beta | H40: =N16*(1+H29*(1-H33)) -> 0.25402862
D41: Cost of Equity | H41: =H37+(H39*H40) -> 0.085088165
D43: WACC | H43: =(H34*H23)+H41*H24 -> 0.076468305
D46: Back to Cover

Sheet Beta
A1: ='Historical Info'!A1 -> Ugar Sugar Works Ltd.
A2: Calculation of Beta
D4: Date | E4: Index Close Price | F4: %Change Monthly | G4: Stock Close Price | H4: %Change Monthly
D5: 44317 | E5: 51937.44 | G5: 29.05 | J5: Index | K5: BSE Sensex
D6: 44348 | E6: 52482.71 | F6: =E6/E5-1 -> 0.010498592 | G6: 35.95 | H6: =G6/G5-1 -> 0.23752151
D7: 44378 | E7: 52586.84 | F7: =E7/E6-1 -> 0.001984082 | G7: 33.65 | H7: =G7/G6-1 -> -0.063977747 | J7: Min (last 52 weeks) | K7: =MIN(G53:G64) -> 35.97
D8: 44409 | E8: 57552.39 | F8: =E8/E7-1 -> 0.094425716 | G8: 27.6 | H8: =G8/G7-1 -> -0.17979198 | J8: Max (Last 52-weeks) | K8: =MAX(G54:G65) -> 50.81
D9: 44440 | E9: 59126.36 | F9: =E9/E8-1 -> 0.027348473 | G9: 28.7 | H9: =G9/G8-1 -> 0.039855072
D10: 44470 | E10: 59306.93 | F10: =E10/E9-1 -> 0.0030539678 | G10: 27 | H10: =G10/G9-1 -> -0.059233449 | J10: Method- 1 (using Slope) | K10: =SLOPE(H6:H64,F6:F64) -> 0.73715171
D11: 44501 | E11: 57064.87 | F11: =E11/E10-1 -> -0.037804351 | G11: 25.9 | H11: =G11/G10-1 -> -0.040740741
D12: 44531 | E12: 58253.82 | F12: =E12/E11-1 -> 0.02083506 | G12: 30.1 | H12: =G12/G11-1 -> 0.16216216 | J12: Method- 2 (ANNOVA) | K12: =K31 -> 0.73715171
D13: 44562 | E13: 58014.17 | F13: =E13/E12-1 -> -0.0041138933 | G13: 33.05 | H13: =G13/G12-1 -> 0.098006645
D14: 44593 | E14: 56247.28 | F14: =E14/E13-1 -> -0.03045618 | G14: 45.8 | H14: =G14/G13-1 -> 0.38577912 | J14: SUMMARY OUTPUT
D15: 44621 | E15: 58568.51 | F15: =E15/E14-1 -> 0.041268307 | G15: 68.5 | H15: =G15/G14-1 -> 0.49563319
D16: 44652 | E16: 57060.87 | F16: =E16/E15-1 -> -0.025741478 | G16: 69.1 | H16: =G16/G15-1 -> 0.0087591241 | J16: Regression Statistics
D17: 44682 | E17: 55566.41 | F17: =E17/E16-1 -> -0.026190628 | G17: 52.7 | H17: =G17/G16-1 -> -0.23733719 | J17: Multiple R | K17: 0.21043708
D18: 44713 | E18: 53018.94 | F18: =E18/E17-1 -> -0.045845503 | G18: 48.6 | H18: =G18/G17-1 -> -0.077798861 | J18: R Square | K18: 0.044283764
D19: 44743 | E19: 57570.25 | F19: =E19/E18-1 -> 0.085843097 | G19: 58.7 | H19: =G19/G18-1 -> 0.20781893 | J19: Adjusted R Square | K19: 0.027516813
D20: 44774 | E20: 59537.07 | F20: =E20/E19-1 -> 0.034163826 | G20: 56.85 | H20: =G20/G19-1 -> -0.031516184 | J20: Standard Error | K20: 0.13865776
D21: 44805 | E21: 57426.92 | F21: =E21/E20-1 -> -0.035442624 | G21: 60.75 | H21: =G21/G20-1 -> 0.068601583 | J21: Observations | K21: 59
D22: 44835 | E22: 60746.59 | F22: =E22/E21-1 -> 0.057806861 | G22: 76.9 | H22: =G22/G21-1 -> 0.26584362
D23: 44866 | E23: 63099.65 | F23: =E23/E22-1 -> 0.038735672 | G23: 90.7 | H23: =G23/G22-1 -> 0.17945384 | J23: ANOVA
D24: 44896 | E24: 60840.74 | F24: =E24/E23-1 -> -0.035799089 | G24: 102.65 | H24: =G24/G23-1 -> 0.13175303 | K24: df | L24: SS | M24: MS | N24: F | O24: Significance F
D25: 44927 | E25: 59549.9 | F25: =E25/E24-1 -> -0.021216704 | G25: 97.45 | H25: =G25/G24-1 -> -0.050657574 | J25: Regression | K25: 1 | L25: 0.050778374 | M25: 0.050778374 | N25: 2.6411339 | O25: 0.10964644
D26: 44958 | E26: 58962.12 | F26: =E26/E25-1 -> -0.0098703776 | G26: 90.1 | H26: =G26/G25-1 -> -0.075423294 | J26: Residual | K26: 57 | L26: 1.0958806 | M26: 0.019225975
D27: 44986 | E27: 58991.52 | F27: =E27/E26-1 -> 0.00049862522 | G27: 92.3 | H27: =G27/G26-1 -> 0.024417314 | J27: Total | K27: 58 | L27: 1.1466589
D28: 45017 | E28: 61112.44 | F28: =E28/E27-1 -> 0.035952964 | G28: 107.14 | H28: =G28/G27-1 -> 0.16078007
D29: 45047 | E29: 62622.24 | F29: =E29/E28-1 -> 0.024705281 | G29: 110.85 | H29: =G29/G28-1 -> 0.03462759 | K29: Coefficients | L29: Standard Error | M29: t Stat | N29: P-value | O29: Lower 95% | P29: Upper 95% | Q29: Lower 95.0% | R29: Upper 95.0%
D30: 45078 | E30: 64718.56 | F30: =E30/E29-1 -> 0.033475647 | G30: 124 | H30: =G30/G29-1 -> 0.11862878 | J30: Intercept | K30: 0.0086043635 | L30: 0.018377341 | M30: 0.46820502 | N30: 0.64142346 | O30: -0.028195627 | P30: 0.045404354 | Q30: -0.028195627 | R30: 0.045404354
D31: 45108 | E31: 66527.67 | F31: =E31/E30-1 -> 0.027953496 | G31: 134.35 | H31: =G31/G30-1 -> 0.083467742 | J31: X Variable 1 | K31: 0.73715171 | L31: 0.45358812 | M31: 1.6251566 | N31: 0.10964644 | O31: -0.17114283 | P31: 1.6454463 | Q31: -0.17114283 | R31: 1.6454463
D32: 45139 | E32: 64831.41 | F32: =E32/E31-1 -> -0.02549706 | G32: 106.7 | H32: =G32/G31-1 -> -0.20580573
D33: 45170 | E33: 65828.41 | F33: =E33/E32-1 -> 0.015378348 | G33: 108.9 | H33: =G33/G32-1 -> 0.020618557
D34: 45200 | E34: 63874.93 | F34: =E34/E33-1 -> -0.029675333 | G34: 95.25 | H34: =G34/G33-1 -> -0.12534435 | J34: Back to Cover
D35: 45231 | E35: 66988.44 | F35: =E35/E34-1 -> 0.04874385 | G35: 90.06 | H35: =G35/G34-1 -> -0.054488189
D36: 45261 | E36: 72240.26 | F36: =E36/E35-1 -> 0.0783989 | G36: 81.86 | H36: =G36/G35-1 -> -0.091050411
D37: 45292 | E37: 71752.11 | F37: =E37/E36-1 -> -0.0067573123 | G37: 80.45 | H37: =G37/G36-1 -> -0.01722453
D38: 45323 | E38: 72500.3 | F38: =E38/E37-1 -> 0.010427429 | G38: 80.35 | H38: =G38/G37-1 -> -0.0012430081
D39: 45352 | E39: 73651.35 | F39: =E39/E38-1 -> 0.015876486 | G39: 65.83 | H39: =G39/G38-1 -> -0.1807094
D40: 45383 | E40: 74482.78 | F40: =E40/E39-1 -> 0.011288727 | G40: 79.67 | H40: =G40/G39-1 -> 0.21023849
D41: 45413 | E41: 73961.31 | F41: =E41/E40-1 -> -0.0070012156 | G41: 72 | H41: =G41/G40-1 -> -0.096272123
D42: 45444 | E42: 79032.73 | F42: =E42/E41-1 -> 0.068568553 | G42: 81.65 | H42: =G42/G41-1 -> 0.13402778
D43: 45474 | E43: 81741.34 | F43: =E43/E42-1 -> 0.034272004 | G43: 84.89 | H43: =G43/G42-1 -> 0.039681568
D44: 45505 | E44: 82365.77 | F44: =E44/E43-1 -> 0.0076390967 | G44: 85.41 | H44: =G44/G43-1 -> 0.0061255743
D45: 45536 | E45: 84299.78 | F45: =E45/E44-1 -> 0.023480749 | G45: 87.62 | H45: =G45/G44-1 -> 0.02587519
D46: 45566 | E46: 79389.06 | F46: =E46/E45-1 -> -0.058253058 | G46: 80.05 | H46: =G46/G45-1 -> -0.0863958
... D64: 46113 | E64: 77453.53 | F64: =E64/E63-1 -> 0.078820358 | G64: 39.23 | H64: =G64/G63-1 -> -0.00050955414

Sheet Summary
A1: Ugar Sugar Works Ltd.
A2: Valuation Summary- Football Field
A4: Football Field Data
F6: Comps | G6: DCF | H6: 52-week High/Low | I6: Market Consensus
D7: High | F7: ='Comps Valuation'!L23 -> 51.375092 | G7: 86.239066 | H7: 50.81 | I7: 83
D8: High | F8: =F7 -> 51.375092 | G8: =G7 -> 86.239066 | H8: =H7 -> 50.81 | I8: =I7 -> 83
D9: Low | F9: =MIN('Comps Valuation'!L23:L25) -> 6.8379946 | G9: 47.786621 | H9: 35.97 | I9: 35
D10: Low | F10: =F9 -> 6.8379946 | G10: =G9 -> 47.786621 | H10: =H9 -> 35.97 | I10: =I9 -> 35
A15: Valuation Summary
D37: Back to Cover
